Workbook

Sheet Инструкция
B2: Модель TCO (Total Cost of Ownership) — кейс «Africa Delivery», горизонт 5 лет
B4: Зачем этот файл
B5: Задача | C5: Оценить полную стоимость владения выбранным архитектурным вариантом на 5 лет и использовать цифры как аргумент в ADR №1 («Выбор архитектурного стиля»).
B6: Как использовать | C6: Заполни один и тот же шаблон для каждого рассматриваемого варианта (например: модульный монолит / SOA / микросервисы) — сравнивать нужно итоги, а не ощущения.
B8: Цветовая легенда
B9: Синий текст на жёлтом фоне | C9: Ячейки для заполнения. Только их и редактируем.
B10: Чёрный текст | C10: Формулы. Не трогаем — пересчитаются сами.
B11: Зелёный текст | C11: Ссылка на лист «Допущения».
B13: Порядок работы
B14: Шаг 1 | C14: Лист «Допущения» → блок 1: вбить драйверы бизнеса по годам (активные пользователи, число заказов, средний чек). Из них считается GMV.
B15: Шаг 2 | C15: Лист «Допущения» → блок 2: финансовые допущения (инфляция, рост ФОТ, ставка дисконтирования, резерв, целевой SLO).
B16: Шаг 3 | C16: Лист «TCO» → в колонке «База, $/год (Год 1)» указать затраты первого года по каждой статье. Лишние статьи оставить пустыми, свои — дописать в свободные строки.
B17: Шаг 4 | C17: Лист «TCO» → в колонке «Драйвер роста» выбрать из выпадающего списка, от чего растёт статья: фикс / инфляция / ФОТ / пользователи / заказы / GMV. Годы 2–5 посчитаются сами.
B18: Шаг 5 | C18: Посмотреть блок «Ключевые метрики» внизу листа «TCO»: итог за 5 лет, NPV, стоимость на заказ, проверку бюджета CFO ($9k/мес на облако).
B20: Что важно не забыть в этом кейсе
B21: Бюджет CFO | C21: $9 000/мес на облако на старте. Если Год 1 в блоке «Облачная инфраструктура» не проходит — это архитектурное решение, а не ошибка модели: опиши, что урезаешь.
B22: Цена простоя | C22: Инвестор оценивает минуту простоя в $12 000. Целевой SLO 99,99% = 52,6 мин/год ≈ $631k. Этот риск считается отдельным блоком — сравни его со стоимостью резервирования.
B23: Транзакционные расходы | C23: Комиссии M-Pesa / Flutterwave / Paystack, SMS и WhatsApp растут с GMV и числом заказов и на горизонте 5 лет обычно обгоняют инфраструктуру. Не забудь их — это типичная ошибка.
B24: Сравнение вариантов | C24: Транзакционные расходы (блок 3) почти одинаковы для любой архитектуры — это pass-through от оборота. Варианты архитектуры сравнивай по блокам 1, 2, 4 и 6.
B25: Разовые затраты | C25: Комплаенс-аудит NDPR/POPIA, пентест, миграция — если статья возникает не каждый год, просто перезапиши формулу в нужной ячейке года числом (и покрась в синий).
B26: Люди | C26: ФОТ команды — обычно самая крупная статья TCO. Микросервисы дешевле в масштабировании, но дороже в эксплуатации: это должно быть видно в цифрах, а не только в тексте ADR.
B28: Все числа в файле — примеры для демонстрации формата. Замени их своими оценками и укажи источник в колонке «Комментарий / источник».

Sheet Допущения
B2: Допущения модели TCO — Africa Delivery
B3: Заполняются только ячейки с жёлтой заливкой. Все числа ниже — пример, заменить своими.
B5: 1. Драйверы бизнеса — заполнить
B6: Показатель | C6: Год 1 | D6: Год 2 | E6: Год 3 | F6: Год 4 | G6: Год 5 | H6: Комментарий / источник
B7: Активные пользователи (на конец года) | C7: 150000 | D7: 600000 | E7: 1500000 | F7: 2500000 | G7: 3500000 | H7: Цель кейса: 1М+ пользователей к 12 месяцам, 5 стран
B8: Число заказов в год | C8: 300000 | D8: 1800000 | E8: 6000000 | F8: 12000000 | G8: 18000000 | H8: MVP: 100 продавцов, 5000 SKU. Оценка студента
B9: Средний чек (AOV), $ | C9: 25 | D9: 26 | E9: 27 | F9: 28 | G9: 29 | H9: Оценка студента по рынку (Jumia / Takealot)
B10: GMV, $ в год (расчёт) | C10: =C8*C9 -> 7500000 | D10: =D8*D9 -> 46800000 | E10: =E8*E9 -> 162000000 | F10: =F8*F9 -> 336000000 | G10: =G8*G9 -> 522000000 | H10: Расчёт: заказы × средний чек
B12: 2. Финансовые допущения — заполнить
B13: Параметр | C13: Значение | H13: Комментарий / источник
B14: Инфляция затрат, % в год | C14: 0.08 | H14: Применяется к статьям с драйвером «инфляция»
B15: Рост ФОТ, % в год | C15: 0.12 | H15: Дефицит ИТ-специалистов на рынке — рост выше инфляции
B16: Ставка дисконтирования, % в год | C16: 0.2 | H16: Для расчёта NPV затрат. Стартап, высокий риск
B17: Резерв на непредвиденное (contingency), % | C17: 0.15 | H17: Надбавка к прямым затратам
B18: Бюджет CFO на облако, $/мес | C18: 5000 | H18: Ограничение из письма CFO
B19: Стоимость минуты простоя, $ | C19: 12000 | H19: Оценка инвестора из условия кейса
B20: Целевой SLO (доступность), % | C20: 0.9999 | H20: Mission critical: 99,99% = 52,6 мин/год
B21: Учитывать стоимость простоя в TCO (1 — да, 0 — нет) | C21: 1 | H21: Переключатель для сценарного анализа
B23: 3. Индексы роста — расчёт, не редактировать
B24: Драйвер | C24: Год 1 | D24: Год 2 | E24: Год 3 | F24: Год 4 | G24: Год 5 | H24: Как считается
B25: фикс | C25: 1 | D25: 1 | E25: 1 | F25: 1 | G25: 1 | H25: Затраты не меняются по годам
B26: инфляция | C26: 1 | D26: =C26*(1+$C$14) -> 1.08 | E26: =D26*(1+$C$14) -> 1.1664 | F26: =E26*(1+$C$14) -> 1.259712 | G26: =F26*(1+$C$14) -> 1.360489 | H26: Год N = Год N-1 × (1 + инфляция)
B27: ФОТ | C27: 1 | D27: =C27*(1+$C$15) -> 1.12 | E27: =D27*(1+$C$15) -> 1.2544 | F27: =E27*(1+$C$15) -> 1.404928 | G27: =F27*(1+$C$15) -> 1.5735194 | H27: Год N = Год N-1 × (1 + рост ФОТ)
B28: пользователи | C28: =C7/$C$7 -> 1 | D28: =D7/$C$7 -> 4 | E28: =E7/$C$7 -> 10 | F28: =F7/$C$7 -> 16.666667 | G28: =G7/$C$7 -> 23.333333 | H28: Пропорционально числу активных пользователей
B29: заказы | C29: =C8/$C$8 -> 1 | D29: =D8/$C$8 -> 6 | E29: =E8/$C$8 -> 20 | F29: =F8/$C$8 -> 40 | G29: =G8/$C$8 -> 60 | H29: Пропорционально числу заказов
B30: GMV | C30: =C10/$C$10 -> 1 | D30: =D10/$C$10 -> 6.24 | E30: =E10/$C$10 -> 21.6 | F30: =F10/$C$10 -> 44.8 | G30: =G10/$C$10 -> 69.6 | H30: Пропорционально обороту
B32: Драйвер «пользователи» — упрощение: облачные расходы редко растут строго линейно (есть эффект масштаба и обратный эффект — рост нагрузки на БД). При желании введи свой драйвер отдельной строкой в таблице индексов.

Sheet TCO Монолит
B2: TCO на 5 лет — Africa Delivery
B3: Заполняем колонки «Драйвер роста» и «База, $/год (Год 1)». Годы 1–5 считаются автоматически.
B5: Статья затрат | C5: Драйвер роста | D5: База, $/год (Год 1) | E5: Год 1 | F5: Год 2 | G5: Год 3 | H5: Год 4 | I5: Год 5 | J5: Итого 5 лет | K5: Доля | L5: Комментарий / источник
B6: БЛОК 1. Облачная инфраструктура (OpEx)
B7: Compute: ноды / контейнеры / serverless | C7: пользователи | D7: 15000 | E7: {=IF($D7="","",$D7*INDEX(Допущения!$C$25:$G$30,MATCH($C7,Допущения!$B$25:$B$30,0),1))} -> 15000 | F7: {=IF($D7="","",$D7*INDEX(Допущения!$C$25:$G$30,MATCH($C7,Допущения!$B$25:$B$30,0),2))} -> 60000 | G7: {=IF($D7="","",$D7*INDEX(Допущения!$C$25:$G$30,MATCH($C7,Допущения!$B$25:$B$30,0),3))} -> 150000 | H7: {=IF($D7="","",$D7*INDEX(Допущения!$C$25:$G$30,MATCH($C7,Допущения!$B$25:$B$30,0),4))} -> 250000 | I7: {=IF($D7="","",$D7*INDEX(Допущения!$C$25:$G$30,MATCH($C7,Допущения!$B$25:$B$30,0),5))} -> 350000 | J7: =SUM(E7:I7) -> 825000 | L7: AWS af-south-1, оценка по калькулятору
B8: Управляемые БД (PostgreSQL, реплики) | C8: пользователи | D8: 12000 | E8: {=IF($D8="","",$D8*INDEX(Допущения!$C$25:$G$30,MATCH($C8,Допущения!$B$25:$B$30,0),1))} -> 12000 | F8: {=IF($D8="","",$D8*INDEX(Допущения!$C$25:$G$30,MATCH($C8,Допущения!$B$25:$B$30,0),2))} -> 48000 | G8: {=IF($D8="","",$D8*INDEX(Допущения!$C$25:$G$30,MATCH($C8,Допущения!$B$25:$B$30,0),3))} -> 120000 | H8: {=IF($D8="","",$D8*INDEX(Допущения!$C$25:$G$30,MATCH($C8,Допущения!$B$25:$B$30,0),4))} -> 200000 | I8: {=IF($D8="","",$D8*INDEX(Допущения!$C$25:$G$30,MATCH($C8,Допущения!$B$25:$B$30,0),5))} -> 280000 | J8: =SUM(E8:I8) -> 660000 | L8: Managed RDS + read replica
B9: Хранилище объектов и резервные копии | C9: пользователи | D9: 6000 | E9: {=IF($D9="","",$D9*INDEX(Допущения!$C$25:$G$30,MATCH($C9,Допущения!$B$25:$B$30,0),1))} -> 6000 | F9: {=IF($D9="","",$D9*INDEX(Допущения!$C$25:$G$30,MATCH($C9,Допущения!$B$25:$B$30,0),2))} -> 24000 | G9: {=IF($D9="","",$D9*INDEX(Допущения!$C$25:$G$30,MATCH($C9,Допущения!$B$25:$B$30,0),3))} -> 60000 | H9: {=IF($D9="","",$D9*INDEX(Допущения!$C$25:$G$30,MATCH($C9,Допущения!$B$25:$B$30,0),4))} -> 100000 | I9: {=IF($D9="","",$D9*INDEX(Допущения!$C$25:$G$30,MATCH($C9,Допущения!$B$25:$B$30,0),5))} -> 140000 | J9: =SUM(E9:I9) -> 330000 | L9: Фото товаров, 5000 SKU на старте
B10: CDN и исходящий трафик | C10: пользователи | D10: 10000 | E10: {=IF($D10="","",$D10*INDEX(Допущения!$C$25:$G$30,MATCH($C10,Допущения!$B$25:$B$30,0),1))} -> 10000 | F10: {=IF($D10="","",$D10*INDEX(Допущения!$C$25:$G$30,MATCH($C10,Допущения!$B$25:$B$30,0),2))} -> 40000 | G10: {=IF($D10="","",$D10*INDEX(Допущения!$C$25:$G$30,MATCH($C10,Допущения!$B$25:$B$30,0),3))} -> 100000 | H10: {=IF($D10="","",$D10*INDEX(Допущения!$C$25:$G$30,MATCH($C10,Допущения!$B$25:$B$30,0),4))} -> 166666.67 | I10: {=IF($D10="","",$D10*INDEX(Допущения!$C$25:$G$30,MATCH($C10,Допущения!$B$25:$B$30,0),5))} -> 233333.33 | J10: =SUM(E10:I10) -> 550000 | L10: 70% трафика — мобильный 3G, картинки WebP
B11: Очереди / стриминг (Kafka, SQS) | C11: пользователи | D11: 0 | E11: {=IF($D11="","",$D11*INDEX(Допущения!$C$25:$G$30,MATCH($C11,Допущения!$B$25:$B$30,0),1))} -> 0 | F11: {=IF($D11="","",$D11*INDEX(Допущения!$C$25:$G$30,MATCH($C11,Допущения!$B$25:$B$30,0),2))} -> 0 | G11: {=IF($D11="","",$D11*INDEX(Допущения!$C$25:$G$30,MATCH($C11,Допущения!$B$25:$B$30,0),3))} -> 0 | H11: {=IF($D11="","",$D11*INDEX(Допущения!$C$25:$G$30,MATCH($C11,Допущения!$B$25:$B$30,0),4))} -> 0 | I11: {=IF($D11="","",$D11*INDEX(Допущения!$C$25:$G$30,MATCH($C11,Допущения!$B$25:$B$30,0),5))} -> 0 | J11: =SUM(E11:I11) -> 0 | L11: Асинхронные заказы и уведомления
B12: Резервный регион / DR | C12: пользователи | D12: 0 | E12: {=IF($D12="","",$D12*INDEX(Допущения!$C$25:$G$30,MATCH($C12,Допущения!$B$25:$B$30,0),1))} -> 0 | F12: {=IF($D12="","",$D12*INDEX(Допущения!$C$25:$G$30,MATCH($C12,Допущения!$B$25:$B$30,0),2))} -> 0 | G12: {=IF($D12="","",$D12*INDEX(Допущения!$C$25:$G$30,MATCH($C12,Допущения!$B$25:$B$30,0),3))} -> 0 | H12: {=IF($D12="","",$D12*INDEX(Допущения!$C$25:$G$30,MATCH($C12,Допущения!$B$25:$B$30,0),4))} -> 0 | I12: {=IF($D12="","",$D12*INDEX(Допущения!$C$25:$G$30,MATCH($C12,Допущения!$B$25:$B$30,0),5))} -> 0 | J12: =SUM(E12:I12) -> 0 | L12: Зависит от выбранной стратегии RTO/RPO
B13: Локальное размещение данных (NDPR, Нигерия) | C13: инфляция | D13: 12000 | E13: {=IF($D13="","",$D13*INDEX(Допущения!$C$25:$G$30,MATCH($C13,Допущения!$B$25:$B$30,0),1))} -> 12000 | F13: {=IF($D13="","",$D13*INDEX(Допущения!$C$25:$G$30,MATCH($C13,Допущения!$B$25:$B$30,0),2))} -> 12960 | G13: {=IF($D13="","",$D13*INDEX(Допущения!$C$25:$G$30,MATCH($C13,Допущения!$B$25:$B$30,0),3))} -> 13996.8 | H13: {=IF($D13="","",$D13*INDEX(Допущения!$C$25:$G$30,MATCH($C13,Допущения!$B$25:$B$30,0),4))} -> 15116.544 | I13: {=IF($D13="","",$D13*INDEX(Допущения!$C$25:$G$30,MATCH($C13,Допущения!$B$25:$B$30,0),5))} -> 16325.868 | J13: =SUM(E13:I13) -> 70399.212 | L13: Локальный провайдер или партнёр — см. ADR №3
C14: фикс | E14: {=IF($D14="","",$D14*INDEX(Допущения!$C$25:$G$30,MATCH($C14,Допущения!$B$25:$B$30,0),1))} | F14: {=IF($D14="","",$D14*INDEX(Допущения!$C$25:$G$30,MATCH($C14,Допущения!$B$25:$B$30,0),2))} | G14: {=IF($D14="","",$D14*INDEX(Допущения!$C$25:$G$30,MATCH($C14,Допущения!$B$25:$B$30,0),3))} | H14: {=IF($D14="","",$D14*INDEX(Допущения!$C$25:$G$30,MATCH($C14,Допущения!$B$25:$B$30,0),4))} | I14: {=IF($D14="","",$D14*INDEX(Допущения!$C$25:$G$30,MATCH($C14,Допущения!$B$25:$B$30,0),5))} | J14: =SUM(E14:I14) -> 0 | L14: Своя статья
B15: Итого по блоку | E15: =SUM(E7:E14) -> 55000 | F15: =SUM(F7:F14) -> 184960 | G15: =SUM(G7:G14) -> 443996.8 | H15: =SUM(H7:H14) -> 731783.21 | I15: =SUM(I7:I14) -> 1019659.2 | J15: =SUM(J7:J14) -> 2435399.2 | K15: =IFERROR(J15/$J$51,0) -> 0.04633372
B17: БЛОК 2. Лицензии, SaaS и инструменты
B18: Observability (метрики, логи, трейсинг) | C18: пользователи | D18: 4000 | E18: {=IF($D18="","",$D18*INDEX(Допущения!$C$25:$G$30,MATCH($C18,Допущения!$B$25:$B$30,0),1))} -> 4000 | F18: {=IF($D18="","",$D18*INDEX(Допущения!$C$25:$G$30,MATCH($C18,Допущения!$B$25:$B$30,0),2))} -> 16000 | G18: {=IF($D18="","",$D18*INDEX(Допущения!$C$25:$G$30,MATCH($C18,Допущения!$B$25:$B$30,0),3))} -> 40000 | H18: {=IF($D18="","",$D18*INDEX(Допущения!$C$25:$G$30,MATCH($C18,Допущения!$B$25:$B$30,0),4))} -> 66666.667 | I18: {=IF($D18="","",$D18*INDEX(Допущения!$C$25:$G$30,MATCH($C18,Допущения!$B$25:$B$30,0),5))} -> 93333.333 | J18: =SUM(E18:I18) -> 220000 | L18: Объём логов растёт с нагрузкой
B19: CI/CD, репозиторий, артефакты | C19: инфляция | D19: 3600 | E19: {=IF($D19="","",$D19*INDEX(Допущения!$C$25:$G$30,MATCH($C19,Допущения!$B$25:$B$30,0),1))} -> 3600 | F19: {=IF($D19="","",$D19*INDEX(Допущения!$C$25:$G$30,MATCH($C19,Допущения!$B$25:$B$30,0),2))} -> 3888 | G19: {=IF($D19="","",$D19*INDEX(Допущения!$C$25:$G$30,MATCH($C19,Допущения!$B$25:$B$30,0),3))} -> 4199.04 | H19: {=IF($D19="","",$D19*INDEX(Допущения!$C$25:$G$30,MATCH($C19,Допущения!$B$25:$B$30,0),4))} -> 4534.9632 | I19: {=IF($D19="","",$D19*INDEX(Допущения!$C$25:$G$30,MATCH($C19,Допущения!$B$25:$B$30,0),5))} -> 4897.7603 | J19: =SUM(E19:I19) -> 21119.763 | L19: GitHub / GitLab, тарифы на команду
B20: Безопасность: WAF, секреты, антифрод | C20: пользователи | D20: 7200 | E20: {=IF($D20="","",$D20*INDEX(Допущения!$C$25:$G$30,MATCH($C20,Допущения!$B$25:$B$30,0),1))} -> 7200 | F20: {=IF($D20="","",$D20*INDEX(Допущения!$C$25:$G$30,MATCH($C20,Допущения!$B$25:$B$30,0),2))} -> 28800 | G20: {=IF($D20="","",$D20*INDEX(Допущения!$C$25:$G$30,MATCH($C20,Допущения!$B$25:$B$30,0),3))} -> 72000 | H20: {=IF($D20="","",$D20*INDEX(Допущения!$C$25:$G$30,MATCH($C20,Допущения!$B$25:$B$30,0),4))} -> 120000 | I20: {=IF($D20="","",$D20*INDEX(Допущения!$C$25:$G$30,MATCH($C20,Допущения!$B$25:$B$30,0),5))} -> 168000 | J20: =SUM(E20:I20) -> 396000 | L20: Мошенничество на ПВЗ — риск из кейса
B21: WhatsApp Business API (подписка) | C21: инфляция | D21: 3000 | E21: {=IF($D21="","",$D21*INDEX(Допущения!$C$25:$G$30,MATCH($C21,Допущения!$B$25:$B$30,0),1))} -> 3000 | F21: {=IF($D21="","",$D21*INDEX(Допущения!$C$25:$G$30,MATCH($C21,Допущения!$B$25:$B$30,0),2))} -> 3240 | G21: {=IF($D21="","",$D21*INDEX(Допущения!$C$25:$G$30,MATCH($C21,Допущения!$B$25:$B$30,0),3))} -> 3499.2 | H21: {=IF($D21="","",$D21*INDEX(Допущения!$C$25:$G$30,MATCH($C21,Допущения!$B$25:$B$30,0),4))} -> 3779.136 | I21: {=IF($D21="","",$D21*INDEX(Допущения!$C$25:$G$30,MATCH($C21,Допущения!$B$25:$B$30,0),5))} -> 4081.4669 | J21: =SUM(E21:I21) -> 17599.803 | L21: Канал для продавцов без личного кабинета
B22: Прочее ПО и подписки | C22: инфляция | D22: 2400 | E22: {=IF($D22="","",$D22*INDEX(Допущения!$C$25:$G$30,MATCH($C22,Допущения!$B$25:$B$30,0),1))} -> 2400 | F22: {=IF($D22="","",$D22*INDEX(Допущения!$C$25:$G$30,MATCH($C22,Допущения!$B$25:$B$30,0),2))} -> 2592 | G22: {=IF($D22="","",$D22*INDEX(Допущения!$C$25:$G$30,MATCH($C22,Допущения!$B$25:$B$30,0),3))} -> 2799.36 | H22: {=IF($D22="","",$D22*INDEX(Допущения!$C$25:$G$30,MATCH($C22,Допущения!$B$25:$B$30,0),4))} -> 3023.3088 | I22: {=IF($D22="","",$D22*INDEX(Допущения!$C$25:$G$30,MATCH($C22,Допущения!$B$25:$B$30,0),5))} -> 3265.1735 | J22: =SUM(E22:I22) -> 14079.842 | L22: Таск-трекер, дизайн, аналитика
C23: фикс | E23: {=IF($D23="","",$D23*INDEX(Допущения!$C$25:$G$30,MATCH($C23,Допущения!$B$25:$B$30,0),1))} | F23: {=IF($D23="","",$D23*INDEX(Допущения!$C$25:$G$30,MATCH($C23,Допущения!$B$25:$B$30,0),2))} | G23: {=IF($D23="","",$D23*INDEX(Допущения!$C$25:$G$30,MATCH($C23,Допущения!$B$25:$B$30,0),3))} | H23: {=IF($D23="","",$D23*INDEX(Допущения!$C$25:$G$30,MATCH($C23,Допущения!$B$25:$B$30,0),4))} | I23: {=IF($D23="","",$D23*INDEX(Допущения!$C$25:$G$30,MATCH($C23,Допущения!$B$25:$B$30,0),5))} | J23: =SUM(E23:I23) -> 0 | L23: Своя статья
B24: Итого по блоку | E24: =SUM(E18:E23) -> 20200 | F24: =SUM(F18:F23) -> 54520 | G24: =SUM(G18:G23) -> 122497.6 | H24: =SUM(H18:H23) -> 198004.07 | I24: =SUM(I18:I23) -> 273577.73 | J24: =SUM(J18:J23) -> 668799.41 | K24: =IFERROR(J24/$J$51,0) -> 0.012723977
B26: БЛОК 3. Транзакционные расходы (Buy / Partner)
B27: Комиссии платёжных провайдеров | C27: GMV | D27: 225000 | E27: {=IF($D27="","",$D27*INDEX(Допущения!$C$25:$G$30,MATCH($C27,Допущения!$B$25:$B$30,0),1))} -> 225000 | F27: {=IF($D27="","",$D27*INDEX(Допущения!$C$25:$G$30,MATCH($C27,Допущения!$B$25:$B$30,0),2))} -> 1404000 | G27: {=IF($D27="","",$D27*INDEX(Допущения!$C$25:$G$30,MATCH($C27,Допущения!$B$25:$B$30,0),3))} -> 4860000 | H27: {=IF($D27="","",$D27*INDEX(Допущения!$C$25:$G$30,MATCH($C27,Допущения!$B$25:$B$30,0),4))} -> 10080000 | I27: {=IF($D27="","",$D27*INDEX(Допущения!$C$25:$G$30,MATCH($C27,Допущения!$B$25:$B$30,0),5))} -> 15660000 | J27: =SUM(E27:I27) -> 32229000 | L27: ≈3% от GMV: M-Pesa (Кения), Flutterwave / Paystack (Нигерия)
B28: SMS-уведомления | C28: заказы | D28: 12000 | E28: {=IF($D28="","",$D28*INDEX(Допущения!$C$25:$G$30,MATCH($C28,Допущения!$B$25:$B$30,0),1))} -> 12000 | F28: {=IF($D28="","",$D28*INDEX(Допущения!$C$25:$G$30,MATCH($C28,Допущения!$B$25:$B$30,0),2))} -> 72000 | G28: {=IF($D28="","",$D28*INDEX(Допущения!$C$25:$G$30,MATCH($C28,Допущения!$B$25:$B$30,0),3))} -> 240000 | H28: {=IF($D28="","",$D28*INDEX(Допущения!$C$25:$G$30,MATCH($C28,Допущения!$B$25:$B$30,0),4))} -> 480000 | I28: {=IF($D28="","",$D28*INDEX(Допущения!$C$25:$G$30,MATCH($C28,Допущения!$B$25:$B$30,0),5))} -> 720000 | J28: =SUM(E28:I28) -> 1524000 | L28: ≈$0,04 за SMS × заказы
B29: WhatsApp-сообщения (за диалог) | C29: заказы | D29: 9000 | E29: {=IF($D29="","",$D29*INDEX(Допущения!$C$25:$G$30,MATCH($C29,Допущения!$B$25:$B$30,0),1))} -> 9000 | F29: {=IF($D29="","",$D29*INDEX(Допущения!$C$25:$G$30,MATCH($C29,Допущения!$B$25:$B$30,0),2))} -> 54000 | G29: {=IF($D29="","",$D29*INDEX(Допущения!$C$25:$G$30,MATCH($C29,Допущения!$B$25:$B$30,0),3))} -> 180000 | H29: {=IF($D29="","",$D29*INDEX(Допущения!$C$25:$G$30,MATCH($C29,Допущения!$B$25:$B$30,0),4))} -> 360000 | I29: {=IF($D29="","",$D29*INDEX(Допущения!$C$25:$G$30,MATCH($C29,Допущения!$B$25:$B$30,0),5))} -> 540000 | J29: =SUM(E29:I29) -> 1143000 | L29: Тариф Meta за conversation
B30: Логистика: интеграции и комиссии партнёров | C30: заказы | D30: 30000 | E30: {=IF($D30="","",$D30*INDEX(Допущения!$C$25:$G$30,MATCH($C30,Допущения!$B$25:$B$30,0),1))} -> 30000 | F30: {=IF($D30="","",$D30*INDEX(Допущения!$C$25:$G$30,MATCH($C30,Допущения!$B$25:$B$30,0),2))} -> 180000 | G30: {=IF($D30="","",$D30*INDEX(Допущения!$C$25:$G$30,MATCH($C30,Допущения!$B$25:$B$30,0),3))} -> 600000 | H30: {=IF($D30="","",$D30*INDEX(Допущения!$C$25:$G$30,MATCH($C30,Допущения!$B$25:$B$30,0),4))} -> 1200000 | I30: {=IF($D30="","",$D30*INDEX(Допущения!$C$25:$G$30,MATCH($C30,Допущения!$B$25:$B$30,0),5))} -> 1800000 | J30: =SUM(E30:I30) -> 3810000 | L30: Sendbox (Нигерия), Sendy (Кения)
C31: фикс | E31: {=IF($D31="","",$D31*INDEX(Допущения!$C$25:$G$30,MATCH($C31,Допущения!$B$25:$B$30,0),1))} | F31: {=IF($D31="","",$D31*INDEX(Допущения!$C$25:$G$30,MATCH($C31,Допущения!$B$25:$B$30,0),2))} | G31: {=IF($D31="","",$D31*INDEX(Допущения!$C$25:$G$30,MATCH($C31,Допущения!$B$25:$B$30,0),3))} | H31: {=IF($D31="","",$D31*INDEX(Допущения!$C$25:$G$30,MATCH($C31,Допущения!$B$25:$B$30,0),4))} | I31: {=IF($D31="","",$D31*INDEX(Допущения!$C$25:$G$30,MATCH($C31,Допущения!$B$25:$B$30,0),5))} | J31: =SUM(E31:I31) -> 0 | L31: Своя статья
B32: Итого по блоку | E32: =SUM(E27:E31) -> 276000 | F32: =SUM(F27:F31) -> 1710000 | G32: =SUM(G27:G31) -> 5880000 | H32: =SUM(H27:H31) -> 12120000 | I32: =SUM(I27:I31) -> 18720000 | J32: =SUM(J27:J31) -> 38706000 | K32: =IFERROR(J32/$J$51,0) -> 0.73638563
B34: БЛОК 4. Команда (ФОТ)
B35: Разработка (FTE × годовая ставка) | C35: ФОТ | D35: 360000 | E35: {=IF($D35="","",$D35*INDEX(Допущения!$C$25:$G$30,MATCH($C35,Допущения!$B$25:$B$30,0),1))} -> 360000 | F35: {=IF($D35="","",$D35*INDEX(Допущения!$C$25:$G$30,MATCH($C35,Допущения!$B$25:$B$30,0),2))} -> 403200 | G35: {=IF($D35="","",$D35*INDEX(Допущения!$C$25:$G$30,MATCH($C35,Допущения!$B$25:$B$30,0),3))} -> 451584 | H35: {=IF($D35="","",$D35*INDEX(Допущения!$C$25:$G$30,MATCH($C35,Допущения!$B$25:$B$30,0),4))} -> 505774.08 | I35: {=IF($D35="","",$D35*INDEX(Допущения!$C$25:$G$30,MATCH($C35,Допущения!$B$25:$B$30,0),5))} -> 566466.97 | J35: =SUM(E35:I35) -> 2287025 | L35: Например 6 FTE × $60k. Зависит от арх. варианта!
B36: DevOps / SRE | C36: ФОТ | D36: 0 | E36: {=IF($D36="","",$D36*INDEX(Допущения!$C$25:$G$30,MATCH($C36,Допущения!$B$25:$B$30,0),1))} -> 0 | F36: {=IF($D36="","",$D36*INDEX(Допущения!$C$25:$G$30,MATCH($C36,Допущения!$B$25:$B$30,0),2))} -> 0 | G36: {=IF($D36="","",$D36*INDEX(Допущения!$C$25:$G$30,MATCH($C36,Допущения!$B$25:$B$30,0),3))} -> 0 | H36: {=IF($D36="","",$D36*INDEX(Допущения!$C$25:$G$30,MATCH($C36,Допущения!$B$25:$B$30,0),4))} -> 0 | I36: {=IF($D36="","",$D36*INDEX(Допущения!$C$25:$G$30,MATCH($C36,Допущения!$B$25:$B$30,0),5))} -> 0 | J36: =SUM(E36:I36) -> 0 | L36: Микросервисы требуют больше SRE, чем монолит
B37: Поддержка и дежурства 24/7 | C37: ФОТ | D37: 24000 | E37: {=IF($D37="","",$D37*INDEX(Допущения!$C$25:$G$30,MATCH($C37,Допущения!$B$25:$B$30,0),1))} -> 24000 | F37: {=IF($D37="","",$D37*INDEX(Допущения!$C$25:$G$30,MATCH($C37,Допущения!$B$25:$B$30,0),2))} -> 26880 | G37: {=IF($D37="","",$D37*INDEX(Допущения!$C$25:$G$30,MATCH($C37,Допущения!$B$25:$B$30,0),3))} -> 30105.6 | H37: {=IF($D37="","",$D37*INDEX(Допущения!$C$25:$G$30,MATCH($C37,Допущения!$B$25:$B$30,0),4))} -> 33718.272 | I37: {=IF($D37="","",$D37*INDEX(Допущения!$C$25:$G$30,MATCH($C37,Допущения!$B$25:$B$30,0),5))} -> 37764.465 | J37: =SUM(E37:I37) -> 152468.34 | L37: Требование mission critical: дежурство ночью
B38: Архитектура и менеджмент | C38: ФОТ | D38: 150000 | E38: {=IF($D38="","",$D38*INDEX(Допущения!$C$25:$G$30,MATCH($C38,Допущения!$B$25:$B$30,0),1))} -> 150000 | F38: {=IF($D38="","",$D38*INDEX(Допущения!$C$25:$G$30,MATCH($C38,Допущения!$B$25:$B$30,0),2))} -> 168000 | G38: {=IF($D38="","",$D38*INDEX(Допущения!$C$25:$G$30,MATCH($C38,Допущения!$B$25:$B$30,0),3))} -> 188160 | H38: {=IF($D38="","",$D38*INDEX(Допущения!$C$25:$G$30,MATCH($C38,Допущения!$B$25:$B$30,0),4))} -> 210739.2 | I38: {=IF($D38="","",$D38*INDEX(Допущения!$C$25:$G$30,MATCH($C38,Допущения!$B$25:$B$30,0),5))} -> 236027.9 | J38: =SUM(E38:I38) -> 952927.1 | L38: Solution Architect, CTO-функция, PM
C39: фикс | E39: {=IF($D39="","",$D39*INDEX(Допущения!$C$25:$G$30,MATCH($C39,Допущения!$B$25:$B$30,0),1))} | F39: {=IF($D39="","",$D39*INDEX(Допущения!$C$25:$G$30,MATCH($C39,Допущения!$B$25:$B$30,0),2))} | G39: {=IF($D39="","",$D39*INDEX(Допущения!$C$25:$G$30,MATCH($C39,Допущения!$B$25:$B$30,0),3))} | H39: {=IF($D39="","",$D39*INDEX(Допущения!$C$25:$G$30,MATCH($C39,Допущения!$B$25:$B$30,0),4))} | I39: {=IF($D39="","",$D39*INDEX(Допущения!$C$25:$G$30,MATCH($C39,Допущения!$B$25:$B$30,0),5))} | J39: =SUM(E39:I39) -> 0 | L39: Своя статья
B40: Итого по блоку | E40: =SUM(E35:E39) -> 534000 | F40: =SUM(F35:F39) -> 598080 | G40: =SUM(G35:G39) -> 669849.6 | H40: =SUM(H35:H39) -> 750231.55 | I40: =SUM(I35:I39) -> 840259.34 | J40: =SUM(J35:J39) -> 3392420.5 | K40: =IFERROR(J40/$J$51,0) -> 0.064541148
B42: БЛОК 5. Разовые затраты и комплаенс
B43: Юридический и комплаенс-аудит (NDPR, POPIA, KICA) | C43: фикс | D43: 25000 | E43: {=IF($D43="","",$D43*INDEX(Допущения!$C$25:$G$30,MATCH($C43,Допущения!$B$25:$B$30,0),1))} -> 25000 | F43: {=IF($D43="","",$D43*INDEX(Допущения!$C$25:$G$30,MATCH($C43,Допущения!$B$25:$B$30,0),2))} -> 25000 | G43: {=IF($D43="","",$D43*INDEX(Допущения!$C$25:$G$30,MATCH($C43,Допущения!$B$25:$B$30,0),3))} -> 25000 | H43: {=IF($D43="","",$D43*INDEX(Допущения!$C$25:$G$30,MATCH($C43,Допущения!$B$25:$B$30,0),4))} -> 25000 | I43: {=IF($D43="","",$D43*INDEX(Допущения!$C$25:$G$30,MATCH($C43,Допущения!$B$25:$B$30,0),5))} -> 25000 | J43: =SUM(E43:I43) -> 125000 | L43: Разовая статья — обнули лишние годы вручную
B44: Пентест и аудит безопасности | C44: инфляция | D44: 15000 | E44: {=IF($D44="","",$D44*INDEX(Допущения!$C$25:$G$30,MATCH($C44,Допущения!$B$25:$B$30,0),1))} -> 15000 | F44: {=IF($D44="","",$D44*INDEX(Допущения!$C$25:$G$30,MATCH($C44,Допущения!$B$25:$B$30,0),2))} -> 16200 | G44: {=IF($D44="","",$D44*INDEX(Допущения!$C$25:$G$30,MATCH($C44,Допущения!$B$25:$B$30,0),3))} -> 17496 | H44: {=IF($D44="","",$D44*INDEX(Допущения!$C$25:$G$30,MATCH($C44,Допущения!$B$25:$B$30,0),4))} -> 18895.68 | I44: {=IF($D44="","",$D44*INDEX(Допущения!$C$25:$G$30,MATCH($C44,Допущения!$B$25:$B$30,0),5))} -> 20407.334 | J44: =SUM(E44:I44) -> 87999.014 | L44: Ежегодно, если mission critical
B45: Миграция данных и интеграции при запуске | C45: фикс | D45: 20000 | E45: {=IF($D45="","",$D45*INDEX(Допущения!$C$25:$G$30,MATCH($C45,Допущения!$B$25:$B$30,0),1))} -> 20000 | F45: {=IF($D45="","",$D45*INDEX(Допущения!$C$25:$G$30,MATCH($C45,Допущения!$B$25:$B$30,0),2))} -> 20000 | G45: {=IF($D45="","",$D45*INDEX(Допущения!$C$25:$G$30,MATCH($C45,Допущения!$B$25:$B$30,0),3))} -> 20000 | H45: {=IF($D45="","",$D45*INDEX(Допущения!$C$25:$G$30,MATCH($C45,Допущения!$B$25:$B$30,0),4))} -> 20000 | I45: {=IF($D45="","",$D45*INDEX(Допущения!$C$25:$G$30,MATCH($C45,Допущения!$B$25:$B$30,0),5))} -> 20000 | J45: =SUM(E45:I45) -> 100000 | L45: Разовая статья
B46: Обучение команды и найм | C46: ФОТ | D46: 30000 | E46: {=IF($D46="","",$D46*INDEX(Допущения!$C$25:$G$30,MATCH($C46,Допущения!$B$25:$B$30,0),1))} -> 30000 | F46: {=IF($D46="","",$D46*INDEX(Допущения!$C$25:$G$30,MATCH($C46,Допущения!$B$25:$B$30,0),2))} -> 33600 | G46: {=IF($D46="","",$D46*INDEX(Допущения!$C$25:$G$30,MATCH($C46,Допущения!$B$25:$B$30,0),3))} -> 37632 | H46: {=IF($D46="","",$D46*INDEX(Допущения!$C$25:$G$30,MATCH($C46,Допущения!$B$25:$B$30,0),4))} -> 42147.84 | I46: {=IF($D46="","",$D46*INDEX(Допущения!$C$25:$G$30,MATCH($C46,Допущения!$B$25:$B$30,0),5))} -> 47205.581 | J46: =SUM(E46:I46) -> 190585.42 | L46: Дефицит локальных ИТ-специалистов
C47: фикс | E47: {=IF($D47="","",$D47*INDEX(Допущения!$C$25:$G$30,MATCH($C47,Допущения!$B$25:$B$30,0),1))} | F47: {=IF($D47="","",$D47*INDEX(Допущения!$C$25:$G$30,MATCH($C47,Допущения!$B$25:$B$30,0),2))} | G47: {=IF($D47="","",$D47*INDEX(Допущения!$C$25:$G$30,MATCH($C47,Допущения!$B$25:$B$30,0),3))} | H47: {=IF($D47="","",$D47*INDEX(Допущения!$C$25:$G$30,MATCH($C47,Допущения!$B$25:$B$30,0),4))} | I47: {=IF($D47="","",$D47*INDEX(Допущения!$C$25:$G$30,MATCH($C47,Допущения!$B$25:$B$30,0),5))} | J47: =SUM(E47:I47) -> 0 | L47: Своя статья
B48: Итого по блоку | E48: =SUM(E43:E47) -> 90000 | F48: =SUM(F43:F47) -> 94800 | G48: =SUM(G43:G47) -> 100128 | H48: =SUM(H43:H47) -> 106043.52 | I48: =SUM(I43:I47) -> 112612.92 | J48: =SUM(J43:J47) -> 503584.44 | K48: =IFERROR(J48/$J$51,0) -> 0.0095807456
B50: Резерв на непредвиденное (contingency) | E50: =(E15+E24+E32+E40+E48)*Допущения!$C$17 -> 146280 | F50: =(F15+F24+F32+F40+F48)*Допущения!$C$17 -> 396354 | G50: =(G15+G24+G32+G40+G48)*Допущения!$C$17 -> 1082470.8 | H50: =(H15+H24+H32+H40+H48)*Допущения!$C$17 -> 2085909.4 | I50: =(I15+I24+I32+I40+I48)*Допущения!$C$17 -> 3144916.4 | J50: =SUM(E50:I50) -> 6855930.5 | L50: Расчёт: сумма блоков 1–5 × ставка резерва с листа «Допущения»
B51: ИТОГО прямые затраты (TCO без учёта простоев) | E51: =E15+E24+E32+E40+E48+E50 -> 1121480 | F51: =F15+F24+F32+F40+F48+F50 -> 3038714 | G51: =G15+G24+G32+G40+G48+G50 -> 8298942.8 | H51: =H15+H24+H32+H40+H48+H50 -> 15991972 | I51: =I15+I24+I32+I40+I48+I50 -> 24111026 | J51: =SUM(E51:I51) -> 52562134
B52: БЛОК 6. Стоимость недоступности (риск)
B53: Ожидаемые потери из-за простоя при целевом SLO | E53: =(1-Допущения!$C$20)*525600*Допущения!$C$19*Допущения!$C$21 -> 630720 | F53: =(1-Допущения!$C$20)*525600*Допущения!$C$19*Допущения!$C$21 -> 630720 | G53: =(1-Допущения!$C$20)*525600*Допущения!$C$19*Допущения!$C$21 -> 630720 | H53: =(1-Допущения!$C$20)*525600*Допущения!$C$19*Допущения!$C$21 -> 630720 | I53: =(1-Допущения!$C$20)*525600*Допущения!$C$19*Допущения!$C$21 -> 630720 | J53: =SUM(E53:I53) -> 3153600 | L53: Расчёт: (1 − SLO) × 525 600 мин/год × стоимость минуты × переключатель. 525 600 — число минут в году
B54: ИТОГО TCO с учётом стоимости простоя | E54: =E51+E53 -> 1752200 | F54: =F51+F53 -> 3669434 | G54: =G51+G53 -> 8929662.8 | H54: =H51+H53 -> 16622692 | I54: =I51+I53 -> 24741746 | J54: =SUM(E54:I54) -> 55715734
B55: Коэффициент дисконтирования | E55: =1/(1+Допущения!$C$16)^0 -> 1 | F55: =1/(1+Допущения!$C$16)^1 -> 0.83333333 | G55: =1/(1+Допущения!$C$16)^2 -> 0.69444444 | H55: =1/(1+Допущения!$C$16)^3 -> 0.5787037 | I55: =1/(1+Допущения!$C$16)^4 -> 0.48225309
B56: Дисконтированный TCO (NPV затрат) | E56: =E54*E55 -> 1752200 | F56: =F54*F55 -> 3057861.7 | G56: =G54*G55 -> 6201154.7 | H56: =H54*H55 -> 9619613.3 | I56: =I54*I55 -> 11931783 | J56: =SUM(E56:I56) -> 32562613
B58: Ключевые метрики
B59: TCO за 5 лет, прямые затраты | E59: =J51 -> 52562134 | L59: Основная цифра для сравнения вариантов в ADR
B60: TCO за 5 лет с учётом простоя | E60: =J54 -> 55715734 | L60: Показывает цену недоступности для mission critical
B61: NPV затрат за 5 лет | E61: =J56 -> 32562613 | L61: Затраты, приведённые к сегодняшнему дню
B62: Средние затраты в год | E62: =J51/5 -> 10512427 | L62: Ориентир для планирования бюджета
B63: Облако, $/мес в Год 1 | E63: =E15/12 -> 4583.3333 | L63: Сравнивается с лимитом CFO
B64: Проверка бюджета CFO на Год 1 | E64: =IF(E15/12<=Допущения!$C$18,"В бюджете CFO","ПРЕВЫШЕНИЕ бюджета") -> В бюджете CFO | L64: Если превышение — объясни в ADR, чем жертвуешь
B65: TCO на 1 заказ за 5 лет | E65: =IFERROR(J51/SUM(Допущения!$C$8:$G$8),0) -> 1.3795836 | L65: Юнит-экономика: сколько ИТ стоит в одном заказе
B66: TCO на 1 активного пользователя (Год 5) | E66: =IFERROR(I51/Допущения!$G$7,0) -> 6.8888644 | L66: Проверка масштабируемости модели
B67: Затраты ИТ как доля GMV за 5 лет | E67: =IFERROR(J51/SUM(Допущения!$C$10:$G$10),0) -> 0.048926868 | L67: Здоровый маркетплейс — единицы процентов
B68: Доля облачной инфраструктуры в TCO | E68: =IFERROR(J15/J51,0) -> 0.04633372 | L68: Обычно меньше, чем ожидают студенты
B69: Доля транзакционных расходов в TCO | E69: =IFERROR(J32/J51,0) -> 0.73638563 | L69: Растёт быстрее всего вместе с GMV
B70: Доля команды (ФОТ) в TCO | E70: =IFERROR(J40/J51,0) -> 0.064541148 | L70: Как правило, крупнейшая статья
B72: Вывод для ADR (заполнить текстом): какой вариант дешевле, за счёт чего, и какие допущения сильнее всего влияют на результат?
B73: Например: вариант «модульный монолит» дешевле на 5 лет за счёт меньшего ФОТ и SRE, но при росте выше 3М пользователей разрыв сокращается — точка пересмотра решения (см. ADR №1).

Sheet TCO EDA
B2: TCO на 5 лет — Africa Delivery
B3: Заполняем колонки «Драйвер роста» и «База, $/год (Год 1)». Годы 1–5 считаются автоматически.
B5: Статья затрат | C5: Драйвер роста | D5: База, $/год (Год 1) | E5: Год 1 | F5: Год 2 | G5: Год 3 | H5: Год 4 | I5: Год 5 | J5: Итого 5 лет | K5: Доля | L5: Комментарий / источник
B6: БЛОК 1. Облачная инфраструктура (OpEx)
B7: Compute: ноды / контейнеры / serverless | C7: пользователи | D7: 25000 | E7: {=IF($D7="","",$D7*INDEX([1]Допущения!$C$25:$G$30,MATCH($C7,[1]Допущения!$B$25:$B$30,0),1))} -> 25000 | F7: {=IF($D7="","",$D7*INDEX([1]Допущения!$C$25:$G$30,MATCH($C7,[1]Допущения!$B$25:$B$30,0),2))} -> 100000 | G7: {=IF($D7="","",$D7*INDEX([1]Допущения!$C$25:$G$30,MATCH($C7,[1]Допущения!$B$25:$B$30,0),3))} -> 250000 | H7: {=IF($D7="","",$D7*INDEX([1]Допущения!$C$25:$G$30,MATCH($C7,[1]Допущения!$B$25:$B$30,0),4))} -> 416666.67 | I7: {=IF($D7="","",$D7*INDEX([1]Допущения!$C$25:$G$30,MATCH($C7,[1]Допущения!$B$25:$B$30,0),5))} -> 583333.33 | J7: =SUM(E7:I7) -> 1375000 | L7: AWS af-south-1, оценка по калькулятору
B8: Управляемые БД (PostgreSQL, реплики) | C8: пользователи | D8: 24000 | E8: {=IF($D8="","",$D8*INDEX([1]Допущения!$C$25:$G$30,MATCH($C8,[1]Допущения!$B$25:$B$30,0),1))} -> 24000 | F8: {=IF($D8="","",$D8*INDEX([1]Допущения!$C$25:$G$30,MATCH($C8,[1]Допущения!$B$25:$B$30,0),2))} -> 96000 | G8: {=IF($D8="","",$D8*INDEX([1]Допущения!$C$25:$G$30,MATCH($C8,[1]Допущения!$B$25:$B$30,0),3))} -> 240000 | H8: {=IF($D8="","",$D8*INDEX([1]Допущения!$C$25:$G$30,MATCH($C8,[1]Допущения!$B$25:$B$30,0),4))} -> 400000 | I8: {=IF($D8="","",$D8*INDEX([1]Допущения!$C$25:$G$30,MATCH($C8,[1]Допущения!$B$25:$B$30,0),5))} -> 560000 | J8: =SUM(E8:I8) -> 1320000 | L8: Managed RDS + read replica
B9: Хранилище объектов и резервные копии | C9: пользователи | D9: 6000 | E9: {=IF($D9="","",$D9*INDEX([1]Допущения!$C$25:$G$30,MATCH($C9,[1]Допущения!$B$25:$B$30,0),1))} -> 6000 | F9: {=IF($D9="","",$D9*INDEX([1]Допущения!$C$25:$G$30,MATCH($C9,[1]Допущения!$B$25:$B$30,0),2))} -> 24000 | G9: {=IF($D9="","",$D9*INDEX([1]Допущения!$C$25:$G$30,MATCH($C9,[1]Допущения!$B$25:$B$30,0),3))} -> 60000 | H9: {=IF($D9="","",$D9*INDEX([1]Допущения!$C$25:$G$30,MATCH($C9,[1]Допущения!$B$25:$B$30,0),4))} -> 100000 | I9: {=IF($D9="","",$D9*INDEX([1]Допущения!$C$25:$G$30,MATCH($C9,[1]Допущения!$B$25:$B$30,0),5))} -> 140000 | J9: =SUM(E9:I9) -> 330000 | L9: Фото товаров, 5000 SKU на старте
B10: CDN и исходящий трафик | C10: пользователи | D10: 12000 | E10: {=IF($D10="","",$D10*INDEX([1]Допущения!$C$25:$G$30,MATCH($C10,[1]Допущения!$B$25:$B$30,0),1))} -> 12000 | F10: {=IF($D10="","",$D10*INDEX([1]Допущения!$C$25:$G$30,MATCH($C10,[1]Допущения!$B$25:$B$30,0),2))} -> 48000 | G10: {=IF($D10="","",$D10*INDEX([1]Допущения!$C$25:$G$30,MATCH($C10,[1]Допущения!$B$25:$B$30,0),3))} -> 120000 | H10: {=IF($D10="","",$D10*INDEX([1]Допущения!$C$25:$G$30,MATCH($C10,[1]Допущения!$B$25:$B$30,0),4))} -> 200000 | I10: {=IF($D10="","",$D10*INDEX([1]Допущения!$C$25:$G$30,MATCH($C10,[1]Допущения!$B$25:$B$30,0),5))} -> 280000 | J10: =SUM(E10:I10) -> 660000 | L10: 70% трафика — мобильный 3G, картинки WebP
B11: Очереди / стриминг (Kafka, SQS) | C11: пользователи | D11: 12000 | E11: {=IF($D11="","",$D11*INDEX([1]Допущения!$C$25:$G$30,MATCH($C11,[1]Допущения!$B$25:$B$30,0),1))} -> 12000 | F11: {=IF($D11="","",$D11*INDEX([1]Допущения!$C$25:$G$30,MATCH($C11,[1]Допущения!$B$25:$B$30,0),2))} -> 48000 | G11: {=IF($D11="","",$D11*INDEX([1]Допущения!$C$25:$G$30,MATCH($C11,[1]Допущения!$B$25:$B$30,0),3))} -> 120000 | H11: {=IF($D11="","",$D11*INDEX([1]Допущения!$C$25:$G$30,MATCH($C11,[1]Допущения!$B$25:$B$30,0),4))} -> 200000 | I11: {=IF($D11="","",$D11*INDEX([1]Допущения!$C$25:$G$30,MATCH($C11,[1]Допущения!$B$25:$B$30,0),5))} -> 280000 | J11: =SUM(E11:I11) -> 660000 | L11: Асинхронные заказы и уведомления
B12: Резервный регион / DR | C12: пользователи | D12: 12000 | E12: {=IF($D12="","",$D12*INDEX([1]Допущения!$C$25:$G$30,MATCH($C12,[1]Допущения!$B$25:$B$30,0),1))} -> 12000 | F12: {=IF($D12="","",$D12*INDEX([1]Допущения!$C$25:$G$30,MATCH($C12,[1]Допущения!$B$25:$B$30,0),2))} -> 48000 | G12: {=IF($D12="","",$D12*INDEX([1]Допущения!$C$25:$G$30,MATCH($C12,[1]Допущения!$B$25:$B$30,0),3))} -> 120000 | H12: {=IF($D12="","",$D12*INDEX([1]Допущения!$C$25:$G$30,MATCH($C12,[1]Допущения!$B$25:$B$30,0),4))} -> 200000 | I12: {=IF($D12="","",$D12*INDEX([1]Допущения!$C$25:$G$30,MATCH($C12,[1]Допущения!$B$25:$B$30,0),5))} -> 280000 | J12: =SUM(E12:I12) -> 660000 | L12: Зависит от выбранной стратегии RTO/RPO
B13: Локальное размещение данных (NDPR, Нигерия) | C13: инфляция | D13: 12000 | E13: {=IF($D13="","",$D13*INDEX([1]Допущения!$C$25:$G$30,MATCH($C13,[1]Допущения!$B$25:$B$30,0),1))} -> 12000 | F13: {=IF($D13="","",$D13*INDEX([1]Допущения!$C$25:$G$30,MATCH($C13,[1]Допущения!$B$25:$B$30,0),2))} -> 12960 | G13: {=IF($D13="","",$D13*INDEX([1]Допущения!$C$25:$G$30,MATCH($C13,[1]Допущения!$B$25:$B$30,0),3))} -> 13996.8 | H13: {=IF($D13="","",$D13*INDEX([1]Допущения!$C$25:$G$30,MATCH($C13,[1]Допущения!$B$25:$B$30,0),4))} -> 15116.544 | I13: {=IF($D13="","",$D13*INDEX([1]Допущения!$C$25:$G$30,MATCH($C13,[1]Допущения!$B$25:$B$30,0),5))} -> 16325.868 | J13: =SUM(E13:I13) -> 70399.212 | L13: Локальный провайдер или партнёр — см. ADR №3
C14: фикс | E14: {=IF($D14="","",$D14*INDEX([1]Допущения!$C$25:$G$30,MATCH($C14,[1]Допущения!$B$25:$B$30,0),1))} | F14: {=IF($D14="","",$D14*INDEX([1]Допущения!$C$25:$G$30,MATCH($C14,[1]Допущения!$B$25:$B$30,0),2))} | G14: {=IF($D14="","",$D14*INDEX([1]Допущения!$C$25:$G$30,MATCH($C14,[1]Допущения!$B$25:$B$30,0),3))} | H14: {=IF($D14="","",$D14*INDEX([1]Допущения!$C$25:$G$30,MATCH($C14,[1]Допущения!$B$25:$B$30,0),4))} | I14: {=IF($D14="","",$D14*INDEX([1]Допущения!$C$25:$G$30,MATCH($C14,[1]Допущения!$B$25:$B$30,0),5))} | J14: =SUM(E14:I14) -> 0 | L14: Своя статья
B15: Итого по блоку | E15: =SUM(E7:E14) -> 103000 | F15: =SUM(F7:F14) -> 376960 | G15: =SUM(G7:G14) -> 923996.8 | H15: =SUM(H7:H14) -> 1531783.2 | I15: =SUM(I7:I14) -> 2139659.2 | J15: =SUM(J7:J14) -> 5075399.2 | K15: =IFERROR(J15/$J$51,0) -> 0.086279668
B17: БЛОК 2. Лицензии, SaaS и инструменты
B18: Observability (метрики, логи, трейсинг) | C18: пользователи | D18: 14000 | E18: {=IF($D18="","",$D18*INDEX([1]Допущения!$C$25:$G$30,MATCH($C18,[1]Допущения!$B$25:$B$30,0),1))} -> 14000 | F18: {=IF($D18="","",$D18*INDEX([1]Допущения!$C$25:$G$30,MATCH($C18,[1]Допущения!$B$25:$B$30,0),2))} -> 56000 | G18: {=IF($D18="","",$D18*INDEX([1]Допущения!$C$25:$G$30,MATCH($C18,[1]Допущения!$B$25:$B$30,0),3))} -> 140000 | H18: {=IF($D18="","",$D18*INDEX([1]Допущения!$C$25:$G$30,MATCH($C18,[1]Допущения!$B$25:$B$30,0),4))} -> 233333.33 | I18: {=IF($D18="","",$D18*INDEX([1]Допущения!$C$25:$G$30,MATCH($C18,[1]Допущения!$B$25:$B$30,0),5))} -> 326666.67 | J18: =SUM(E18:I18) -> 770000 | L18: Объём логов растёт с нагрузкой
B19: CI/CD, репозиторий, артефакты | C19: инфляция | D19: 4800 | E19: {=IF($D19="","",$D19*INDEX([1]Допущения!$C$25:$G$30,MATCH($C19,[1]Допущения!$B$25:$B$30,0),1))} -> 4800 | F19: {=IF($D19="","",$D19*INDEX([1]Допущения!$C$25:$G$30,MATCH($C19,[1]Допущения!$B$25:$B$30,0),2))} -> 5184 | G19: {=IF($D19="","",$D19*INDEX([1]Допущения!$C$25:$G$30,MATCH($C19,[1]Допущения!$B$25:$B$30,0),3))} -> 5598.72 | H19: {=IF($D19="","",$D19*INDEX([1]Допущения!$C$25:$G$30,MATCH($C19,[1]Допущения!$B$25:$B$30,0),4))} -> 6046.6176 | I19: {=IF($D19="","",$D19*INDEX([1]Допущения!$C$25:$G$30,MATCH($C19,[1]Допущения!$B$25:$B$30,0),5))} -> 6530.347 | J19: =SUM(E19:I19) -> 28159.685 | L19: GitHub / GitLab, тарифы на команду
B20: Безопасность: WAF, секреты, антифрод | C20: пользователи | D20: 7200 | E20: {=IF($D20="","",$D20*INDEX([1]Допущения!$C$25:$G$30,MATCH($C20,[1]Допущения!$B$25:$B$30,0),1))} -> 7200 | F20: {=IF($D20="","",$D20*INDEX([1]Допущения!$C$25:$G$30,MATCH($C20,[1]Допущения!$B$25:$B$30,0),2))} -> 28800 | G20: {=IF($D20="","",$D20*INDEX([1]Допущения!$C$25:$G$30,MATCH($C20,[1]Допущения!$B$25:$B$30,0),3))} -> 72000 | H20: {=IF($D20="","",$D20*INDEX([1]Допущения!$C$25:$G$30,MATCH($C20,[1]Допущения!$B$25:$B$30,0),4))} -> 120000 | I20: {=IF($D20="","",$D20*INDEX([1]Допущения!$C$25:$G$30,MATCH($C20,[1]Допущения!$B$25:$B$30,0),5))} -> 168000 | J20: =SUM(E20:I20) -> 396000 | L20: Мошенничество на ПВЗ — риск из кейса
B21: WhatsApp Business API (подписка) | C21: инфляция | D21: 3000 | E21: {=IF($D21="","",$D21*INDEX([1]Допущения!$C$25:$G$30,MATCH($C21,[1]Допущения!$B$25:$B$30,0),1))} -> 3000 | F21: {=IF($D21="","",$D21*INDEX([1]Допущения!$C$25:$G$30,MATCH($C21,[1]Допущения!$B$25:$B$30,0),2))} -> 3240 | G21: {=IF($D21="","",$D21*INDEX([1]Допущения!$C$25:$G$30,MATCH($C21,[1]Допущения!$B$25:$B$30,0),3))} -> 3499.2 | H21: {=IF($D21="","",$D21*INDEX([1]Допущения!$C$25:$G$30,MATCH($C21,[1]Допущения!$B$25:$B$30,0),4))} -> 3779.136 | I21: {=IF($D21="","",$D21*INDEX([1]Допущения!$C$25:$G$30,MATCH($C21,[1]Допущения!$B$25:$B$30,0),5))} -> 4081.4669 | J21: =SUM(E21:I21) -> 17599.803 | L21: Канал для продавцов без личного кабинета
B22: Прочее ПО и подписки | C22: инфляция | D22: 2400 | E22: {=IF($D22="","",$D22*INDEX([1]Допущения!$C$25:$G$30,MATCH($C22,[1]Допущения!$B$25:$B$30,0),1))} -> 2400 | F22: {=IF($D22="","",$D22*INDEX([1]Допущения!$C$25:$G$30,MATCH($C22,[1]Допущения!$B$25:$B$30,0),2))} -> 2592 | G22: {=IF($D22="","",$D22*INDEX([1]Допущения!$C$25:$G$30,MATCH($C22,[1]Допущения!$B$25:$B$30,0),3))} -> 2799.36 | H22: {=IF($D22="","",$D22*INDEX([1]Допущения!$C$25:$G$30,MATCH($C22,[1]Допущения!$B$25:$B$30,0),4))} -> 3023.3088 | I22: {=IF($D22="","",$D22*INDEX([1]Допущения!$C$25:$G$30,MATCH($C22,[1]Допущения!$B$25:$B$30,0),5))} -> 3265.1735 | J22: =SUM(E22:I22) -> 14079.842 | L22: Таск-трекер, дизайн, аналитика
C23: фикс | E23: {=IF($D23="","",$D23*INDEX([1]Допущения!$C$25:$G$30,MATCH($C23,[1]Допущения!$B$25:$B$30,0),1))} | F23: {=IF($D23="","",$D23*INDEX([1]Допущения!$C$25:$G$30,MATCH($C23,[1]Допущения!$B$25:$B$30,0),2))} | G23: {=IF($D23="","",$D23*INDEX([1]Допущения!$C$25:$G$30,MATCH($C23,[1]Допущения!$B$25:$B$30,0),3))} | H23: {=IF($D23="","",$D23*INDEX([1]Допущения!$C$25:$G$30,MATCH($C23,[1]Допущения!$B$25:$B$30,0),4))} | I23: {=IF($D23="","",$D23*INDEX([1]Допущения!$C$25:$G$30,MATCH($C23,[1]Допущения!$B$25:$B$30,0),5))} | J23: =SUM(E23:I23) -> 0 | L23: Своя статья
B24: Итого по блоку | E24: =SUM(E18:E23) -> 31400 | F24: =SUM(F18:F23) -> 95816 | G24: =SUM(G18:G23) -> 223897.28 | H24: =SUM(H18:H23) -> 366182.4 | I24: =SUM(I18:I23) -> 508543.65 | J24: =SUM(J18:J23) -> 1225839.3 | K24: =IFERROR(J24/$J$51,0) -> 0.020838757
B26: БЛОК 3. Транзакционные расходы (Buy / Partner)
B27: Комиссии платёжных провайдеров | C27: GMV | D27: 225000 | E27: {=IF($D27="","",$D27*INDEX([1]Допущения!$C$25:$G$30,MATCH($C27,[1]Допущения!$B$25:$B$30,0),1))} -> 225000 | F27: {=IF($D27="","",$D27*INDEX([1]Допущения!$C$25:$G$30,MATCH($C27,[1]Допущения!$B$25:$B$30,0),2))} -> 1404000 | G27: {=IF($D27="","",$D27*INDEX([1]Допущения!$C$25:$G$30,MATCH($C27,[1]Допущения!$B$25:$B$30,0),3))} -> 4860000 | H27: {=IF($D27="","",$D27*INDEX([1]Допущения!$C$25:$G$30,MATCH($C27,[1]Допущения!$B$25:$B$30,0),4))} -> 10080000 | I27: {=IF($D27="","",$D27*INDEX([1]Допущения!$C$25:$G$30,MATCH($C27,[1]Допущения!$B$25:$B$30,0),5))} -> 15660000 | J27: =SUM(E27:I27) -> 32229000 | L27: ≈3% от GMV: M-Pesa (Кения), Flutterwave / Paystack (Нигерия)
B28: SMS-уведомления | C28: заказы | D28: 12000 | E28: {=IF($D28="","",$D28*INDEX([1]Допущения!$C$25:$G$30,MATCH($C28,[1]Допущения!$B$25:$B$30,0),1))} -> 12000 | F28: {=IF($D28="","",$D28*INDEX([1]Допущения!$C$25:$G$30,MATCH($C28,[1]Допущения!$B$25:$B$30,0),2))} -> 72000 | G28: {=IF($D28="","",$D28*INDEX([1]Допущения!$C$25:$G$30,MATCH($C28,[1]Допущения!$B$25:$B$30,0),3))} -> 240000 | H28: {=IF($D28="","",$D28*INDEX([1]Допущения!$C$25:$G$30,MATCH($C28,[1]Допущения!$B$25:$B$30,0),4))} -> 480000 | I28: {=IF($D28="","",$D28*INDEX([1]Допущения!$C$25:$G$30,MATCH($C28,[1]Допущения!$B$25:$B$30,0),5))} -> 720000 | J28: =SUM(E28:I28) -> 1524000 | L28: ≈$0,04 за SMS × заказы
B29: WhatsApp-сообщения (за диалог) | C29: заказы | D29: 9000 | E29: {=IF($D29="","",$D29*INDEX([1]Допущения!$C$25:$G$30,MATCH($C29,[1]Допущения!$B$25:$B$30,0),1))} -> 9000 | F29: {=IF($D29="","",$D29*INDEX([1]Допущения!$C$25:$G$30,MATCH($C29,[1]Допущения!$B$25:$B$30,0),2))} -> 54000 | G29: {=IF($D29="","",$D29*INDEX([1]Допущения!$C$25:$G$30,MATCH($C29,[1]Допущения!$B$25:$B$30,0),3))} -> 180000 | H29: {=IF($D29="","",$D29*INDEX([1]Допущения!$C$25:$G$30,MATCH($C29,[1]Допущения!$B$25:$B$30,0),4))} -> 360000 | I29: {=IF($D29="","",$D29*INDEX([1]Допущения!$C$25:$G$30,MATCH($C29,[1]Допущения!$B$25:$B$30,0),5))} -> 540000 | J29: =SUM(E29:I29) -> 1143000 | L29: Тариф Meta за conversation
B30: Логистика: интеграции и комиссии партнёров | C30: заказы | D30: 30000 | E30: {=IF($D30="","",$D30*INDEX([1]Допущения!$C$25:$G$30,MATCH($C30,[1]Допущения!$B$25:$B$30,0),1))} -> 30000 | F30: {=IF($D30="","",$D30*INDEX([1]Допущения!$C$25:$G$30,MATCH($C30,[1]Допущения!$B$25:$B$30,0),2))} -> 180000 | G30: {=IF($D30="","",$D30*INDEX([1]Допущения!$C$25:$G$30,MATCH($C30,[1]Допущения!$B$25:$B$30,0),3))} -> 600000 | H30: {=IF($D30="","",$D30*INDEX([1]Допущения!$C$25:$G$30,MATCH($C30,[1]Допущения!$B$25:$B$30,0),4))} -> 1200000 | I30: {=IF($D30="","",$D30*INDEX([1]Допущения!$C$25:$G$30,MATCH($C30,[1]Допущения!$B$25:$B$30,0),5))} -> 1800000 | J30: =SUM(E30:I30) -> 3810000 | L30: Sendbox (Нигерия), Sendy (Кения)
C31: фикс | E31: {=IF($D31="","",$D31*INDEX([1]Допущения!$C$25:$G$30,MATCH($C31,[1]Допущения!$B$25:$B$30,0),1))} | F31: {=IF($D31="","",$D31*INDEX([1]Допущения!$C$25:$G$30,MATCH($C31,[1]Допущения!$B$25:$B$30,0),2))} | G31: {=IF($D31="","",$D31*INDEX([1]Допущения!$C$25:$G$30,MATCH($C31,[1]Допущения!$B$25:$B$30,0),3))} | H31: {=IF($D31="","",$D31*INDEX([1]Допущения!$C$25:$G$30,MATCH($C31,[1]Допущения!$B$25:$B$30,0),4))} | I31: {=IF($D31="","",$D31*INDEX([1]Допущения!$C$25:$G$30,MATCH($C31,[1]Допущения!$B$25:$B$30,0),5))} | J31: =SUM(E31:I31) -> 0 | L31: Своя статья
B32: Итого по блоку | E32: =SUM(E27:E31) -> 276000 | F32: =SUM(F27:F31) -> 1710000 | G32: =SUM(G27:G31) -> 5880000 | H32: =SUM(H27:H31) -> 12120000 | I32: =SUM(I27:I31) -> 18720000 | J32: =SUM(J27:J31) -> 38706000 | K32: =IFERROR(J32/$J$51,0) -> 0.65798584
B34: БЛОК 4. Команда (ФОТ)
B35: Разработка (FTE × годовая ставка) | C35: ФОТ | D35: 600000 | E35: {=IF($D35="","",$D35*INDEX([1]Допущения!$C$25:$G$30,MATCH($C35,[1]Допущения!$B$25:$B$30,0),1))} -> 600000 | F35: {=IF($D35="","",$D35*INDEX([1]Допущения!$C$25:$G$30,MATCH($C35,[1]Допущения!$B$25:$B$30,0),2))} -> 672000 | G35: {=IF($D35="","",$D35*INDEX([1]Допущения!$C$25:$G$30,MATCH($C35,[1]Допущения!$B$25:$B$30,0),3))} -> 752640 | H35: {=IF($D35="","",$D35*INDEX([1]Допущения!$C$25:$G$30,MATCH($C35,[1]Допущения!$B$25:$B$30,0),4))} -> 842956.8 | I35: {=IF($D35="","",$D35*INDEX([1]Допущения!$C$25:$G$30,MATCH($C35,[1]Допущения!$B$25:$B$30,0),5))} -> 944111.62 | J35: =SUM(E35:I35) -> 3811708.4 | L35: Например 6 FTE × $60k. Зависит от арх. варианта!
B36: DevOps / SRE | C36: ФОТ | D36: 90000 | E36: {=IF($D36="","",$D36*INDEX([1]Допущения!$C$25:$G$30,MATCH($C36,[1]Допущения!$B$25:$B$30,0),1))} -> 90000 | F36: {=IF($D36="","",$D36*INDEX([1]Допущения!$C$25:$G$30,MATCH($C36,[1]Допущения!$B$25:$B$30,0),2))} -> 100800 | G36: {=IF($D36="","",$D36*INDEX([1]Допущения!$C$25:$G$30,MATCH($C36,[1]Допущения!$B$25:$B$30,0),3))} -> 112896 | H36: {=IF($D36="","",$D36*INDEX([1]Допущения!$C$25:$G$30,MATCH($C36,[1]Допущения!$B$25:$B$30,0),4))} -> 126443.52 | I36: {=IF($D36="","",$D36*INDEX([1]Допущения!$C$25:$G$30,MATCH($C36,[1]Допущения!$B$25:$B$30,0),5))} -> 141616.74 | J36: =SUM(E36:I36) -> 571756.26 | L36: Микросервисы требуют больше SRE, чем монолит
B37: Поддержка и дежурства 24/7 | C37: ФОТ | D37: 48000 | E37: {=IF($D37="","",$D37*INDEX([1]Допущения!$C$25:$G$30,MATCH($C37,[1]Допущения!$B$25:$B$30,0),1))} -> 48000 | F37: {=IF($D37="","",$D37*INDEX([1]Допущения!$C$25:$G$30,MATCH($C37,[1]Допущения!$B$25:$B$30,0),2))} -> 53760 | G37: {=IF($D37="","",$D37*INDEX([1]Допущения!$C$25:$G$30,MATCH($C37,[1]Допущения!$B$25:$B$30,0),3))} -> 60211.2 | H37: {=IF($D37="","",$D37*INDEX([1]Допущения!$C$25:$G$30,MATCH($C37,[1]Допущения!$B$25:$B$30,0),4))} -> 67436.544 | I37: {=IF($D37="","",$D37*INDEX([1]Допущения!$C$25:$G$30,MATCH($C37,[1]Допущения!$B$25:$B$30,0),5))} -> 75528.929 | J37: =SUM(E37:I37) -> 304936.67 | L37: Требование mission critical: дежурство ночью
B38: Архитектура и менеджмент | C38: ФОТ | D38: 150000 | E38: {=IF($D38="","",$D38*INDEX([1]Допущения!$C$25:$G$30,MATCH($C38,[1]Допущения!$B$25:$B$30,0),1))} -> 150000 | F38: {=IF($D38="","",$D38*INDEX([1]Допущения!$C$25:$G$30,MATCH($C38,[1]Допущения!$B$25:$B$30,0),2))} -> 168000 | G38: {=IF($D38="","",$D38*INDEX([1]Допущения!$C$25:$G$30,MATCH($C38,[1]Допущения!$B$25:$B$30,0),3))} -> 188160 | H38: {=IF($D38="","",$D38*INDEX([1]Допущения!$C$25:$G$30,MATCH($C38,[1]Допущения!$B$25:$B$30,0),4))} -> 210739.2 | I38: {=IF($D38="","",$D38*INDEX([1]Допущения!$C$25:$G$30,MATCH($C38,[1]Допущения!$B$25:$B$30,0),5))} -> 236027.9 | J38: =SUM(E38:I38) -> 952927.1 | L38: Solution Architect, CTO-функция, PM
C39: фикс | E39: {=IF($D39="","",$D39*INDEX([1]Допущения!$C$25:$G$30,MATCH($C39,[1]Допущения!$B$25:$B$30,0),1))} | F39: {=IF($D39="","",$D39*INDEX([1]Допущения!$C$25:$G$30,MATCH($C39,[1]Допущения!$B$25:$B$30,0),2))} | G39: {=IF($D39="","",$D39*INDEX([1]Допущения!$C$25:$G$30,MATCH($C39,[1]Допущения!$B$25:$B$30,0),3))} | H39: {=IF($D39="","",$D39*INDEX([1]Допущения!$C$25:$G$30,MATCH($C39,[1]Допущения!$B$25:$B$30,0),4))} | I39: {=IF($D39="","",$D39*INDEX([1]Допущения!$C$25:$G$30,MATCH($C39,[1]Допущения!$B$25:$B$30,0),5))} | J39: =SUM(E39:I39) -> 0 | L39: Своя статья
B40: Итого по блоку | E40: =SUM(E35:E39) -> 888000 | F40: =SUM(F35:F39) -> 994560 | G40: =SUM(G35:G39) -> 1113907.2 | H40: =SUM(H35:H39) -> 1247576.1 | I40: =SUM(I35:I39) -> 1397285.2 | J40: =SUM(J35:J39) -> 5641328.5 | K40: =IFERROR(J40/$J$51,0) -> 0.095900228
B42: БЛОК 5. Разовые затраты и комплаенс
B43: Юридический и комплаенс-аудит (NDPR, POPIA, KICA) | C43: фикс | D43: 25000 | E43: {=IF($D43="","",$D43*INDEX([1]Допущения!$C$25:$G$30,MATCH($C43,[1]Допущения!$B$25:$B$30,0),1))} -> 25000 | F43: {=IF($D43="","",$D43*INDEX([1]Допущения!$C$25:$G$30,MATCH($C43,[1]Допущения!$B$25:$B$30,0),2))} -> 25000 | G43: {=IF($D43="","",$D43*INDEX([1]Допущения!$C$25:$G$30,MATCH($C43,[1]Допущения!$B$25:$B$30,0),3))} -> 25000 | H43: {=IF($D43="","",$D43*INDEX([1]Допущения!$C$25:$G$30,MATCH($C43,[1]Допущения!$B$25:$B$30,0),4))} -> 25000 | I43: {=IF($D43="","",$D43*INDEX([1]Допущения!$C$25:$G$30,MATCH($C43,[1]Допущения!$B$25:$B$30,0),5))} -> 25000 | J43: =SUM(E43:I43) -> 125000 | L43: Разовая статья — обнули лишние годы вручную
B44: Пентест и аудит безопасности | C44: инфляция | D44: 15000 | E44: {=IF($D44="","",$D44*INDEX([1]Допущения!$C$25:$G$30,MATCH($C44,[1]Допущения!$B$25:$B$30,0),1))} -> 15000 | F44: {=IF($D44="","",$D44*INDEX([1]Допущения!$C$25:$G$30,MATCH($C44,[1]Допущения!$B$25:$B$30,0),2))} -> 16200 | G44: {=IF($D44="","",$D44*INDEX([1]Допущения!$C$25:$G$30,MATCH($C44,[1]Допущения!$B$25:$B$30,0),3))} -> 17496 | H44: {=IF($D44="","",$D44*INDEX([1]Допущения!$C$25:$G$30,MATCH($C44,[1]Допущения!$B$25:$B$30,0),4))} -> 18895.68 | I44: {=IF($D44="","",$D44*INDEX([1]Допущения!$C$25:$G$30,MATCH($C44,[1]Допущения!$B$25:$B$30,0),5))} -> 20407.334 | J44: =SUM(E44:I44) -> 87999.014 | L44: Ежегодно, если mission critical
B45: Миграция данных и интеграции при запуске | C45: фикс | D45: 20000 | E45: {=IF($D45="","",$D45*INDEX([1]Допущения!$C$25:$G$30,MATCH($C45,[1]Допущения!$B$25:$B$30,0),1))} -> 20000 | F45: {=IF($D45="","",$D45*INDEX([1]Допущения!$C$25:$G$30,MATCH($C45,[1]Допущения!$B$25:$B$30,0),2))} -> 20000 | G45: {=IF($D45="","",$D45*INDEX([1]Допущения!$C$25:$G$30,MATCH($C45,[1]Допущения!$B$25:$B$30,0),3))} -> 20000 | H45: {=IF($D45="","",$D45*INDEX([1]Допущения!$C$25:$G$30,MATCH($C45,[1]Допущения!$B$25:$B$30,0),4))} -> 20000 | I45: {=IF($D45="","",$D45*INDEX([1]Допущения!$C$25:$G$30,MATCH($C45,[1]Допущения!$B$25:$B$30,0),5))} -> 20000 | J45: =SUM(E45:I45) -> 100000 | L45: Разовая статья
B46: Обучение команды и найм | C46: ФОТ | D46: 30000 | E46: {=IF($D46="","",$D46*INDEX([1]Допущения!$C$25:$G$30,MATCH($C46,[1]Допущения!$B$25:$B$30,0),1))} -> 30000 | F46: {=IF($D46="","",$D46*INDEX([1]Допущения!$C$25:$G$30,MATCH($C46,[1]Допущения!$B$25:$B$30,0),2))} -> 33600 | G46: {=IF($D46="","",$D46*INDEX([1]Допущения!$C$25:$G$30,MATCH($C46,[1]Допущения!$B$25:$B$30,0),3))} -> 37632 | H46: {=IF($D46="","",$D46*INDEX([1]Допущения!$C$25:$G$30,MATCH($C46,[1]Допущения!$B$25:$B$30,0),4))} -> 42147.84 | I46: {=IF($D46="","",$D46*INDEX([1]Допущения!$C$25:$G$30,MATCH($C46,[1]Допущения!$B$25:$B$30,0),5))} -> 47205.581 | J46: =SUM(E46:I46) -> 190585.42 | L46: Дефицит локальных ИТ-специалистов
C47: фикс | E47: {=IF($D47="","",$D47*INDEX([1]Допущения!$C$25:$G$30,MATCH($C47,[1]Допущения!$B$25:$B$30,0),1))} | F47: {=IF($D47="","",$D47*INDEX([1]Допущения!$C$25:$G$30,MATCH($C47,[1]Допущения!$B$25:$B$30,0),2))} | G47: {=IF($D47="","",$D47*INDEX([1]Допущения!$C$25:$G$30,MATCH($C47,[1]Допущения!$B$25:$B$30,0),3))} | H47: {=IF($D47="","",$D47*INDEX([1]Допущения!$C$25:$G$30,MATCH($C47,[1]Допущения!$B$25:$B$30,0),4))} | I47: {=IF($D47="","",$D47*INDEX([1]Допущения!$C$25:$G$30,MATCH($C47,[1]Допущения!$B$25:$B$30,0),5))} | J47: =SUM(E47:I47) -> 0 | L47: Своя статья
B48: Итого по блоку | E48: =SUM(E43:E47) -> 90000 | F48: =SUM(F43:F47) -> 94800 | G48: =SUM(G43:G47) -> 100128 | H48: =SUM(H43:H47) -> 106043.52 | I48: =SUM(I43:I47) -> 112612.92 | J48: =SUM(J43:J47) -> 503584.44 | K48: =IFERROR(J48/$J$51,0) -> 0.0085607251
B50: Резерв на непредвиденное (contingency) | E50: =(E15+E24+E32+E40+E48)*[1]Допущения!$C$17 -> 208260 | F50: =(F15+F24+F32+F40+F48)*[1]Допущения!$C$17 -> 490820.4 | G50: =(G15+G24+G32+G40+G48)*[1]Допущения!$C$17 -> 1236289.4 | H50: =(H15+H24+H32+H40+H48)*[1]Допущения!$C$17 -> 2305737.8 | I50: =(I15+I24+I32+I40+I48)*[1]Допущения!$C$17 -> 3431715.1 | J50: =SUM(E50:I50) -> 7672822.7 | L50: Расчёт: сумма блоков 1–5 × ставка резерва с листа «Допущения»
B51: ИТОГО прямые затраты (TCO без учёта простоев) | E51: =E15+E24+E32+E40+E48+E50 -> 1596660 | F51: =F15+F24+F32+F40+F48+F50 -> 3762956.4 | G51: =G15+G24+G32+G40+G48+G50 -> 9478218.7 | H51: =H15+H24+H32+H40+H48+H50 -> 17677323 | I51: =I15+I24+I32+I40+I48+I50 -> 26309816 | J51: =SUM(E51:I51) -> 58824974
B52: БЛОК 6. Стоимость недоступности (риск)
B53: Ожидаемые потери из-за простоя при целевом SLO | E53: =(1-[1]Допущения!$C$20)*525600*[1]Допущения!$C$19*[1]Допущения!$C$21 -> 630720 | F53: =(1-[1]Допущения!$C$20)*525600*[1]Допущения!$C$19*[1]Допущения!$C$21 -> 630720 | G53: =(1-[1]Допущения!$C$20)*525600*[1]Допущения!$C$19*[1]Допущения!$C$21 -> 630720 | H53: =(1-[1]Допущения!$C$20)*525600*[1]Допущения!$C$19*[1]Допущения!$C$21 -> 630720 | I53: =(1-[1]Допущения!$C$20)*525600*[1]Допущения!$C$19*[1]Допущения!$C$21 -> 630720 | J53: =SUM(E53:I53) -> 3153600 | L53: Расчёт: (1 − SLO) × 525 600 мин/год × стоимость минуты × переключатель. 525 600 — число минут в году
B54: ИТОГО TCO с учётом стоимости простоя | E54: =E51+E53 -> 2227380 | F54: =F51+F53 -> 4393676.4 | G54: =G51+G53 -> 10108939 | H54: =H51+H53 -> 18308043 | I54: =I51+I53 -> 26940536 | J54: =SUM(E54:I54) -> 61978574
B55: Коэффициент дисконтирования | E55: =1/(1+[1]Допущения!$C$16)^0 -> 1 | F55: =1/(1+[1]Допущения!$C$16)^1 -> 0.83333333 | G55: =1/(1+[1]Допущения!$C$16)^2 -> 0.69444444 | H55: =1/(1+[1]Допущения!$C$16)^3 -> 0.5787037 | I55: =1/(1+[1]Допущения!$C$16)^4 -> 0.48225309
B56: Дисконтированный TCO (NPV затрат) | E56: =E54*E55 -> 2227380 | F56: =F54*F55 -> 3661397 | G56: =G54*G55 -> 7020096.3 | H56: =H54*H55 -> 10594932 | I56: =I54*I55 -> 12992157 | J56: =SUM(E56:I56) -> 36495962
B58: Ключевые метрики
B59: TCO за 5 лет, прямые затраты | E59: =J51 -> 58824974 | L59: Основная цифра для сравнения вариантов в ADR
B60: TCO за 5 лет с учётом простоя | E60: =J54 -> 61978574 | L60: Показывает цену недоступности для mission critical
B61: NPV затрат за 5 лет | E61: =J56 -> 36495962 | L61: Затраты, приведённые к сегодняшнему дню
B62: Средние затраты в год | E62: =J51/5 -> 11764995 | L62: Ориентир для планирования бюджета
B63: Облако, $/мес в Год 1 | E63: =E15/12 -> 8583.3333 | L63: Сравнивается с лимитом CFO
B64: Проверка бюджета CFO на Год 1 | E64: =IF(E15/12<=[1]Допущения!$C$18,"В бюджете CFO","ПРЕВЫШЕНИЕ бюджета") -> В бюджете CFO | L64: Если превышение — объясни в ADR, чем жертвуешь
B65: TCO на 1 заказ за 5 лет | E65: =IFERROR(J51/SUM([1]Допущения!$C$8:$G$8),0) -> 1.5439626 | L65: Юнит-экономика: сколько ИТ стоит в одном заказе
B66: TCO на 1 активного пользователя (Год 5) | E66: =IFERROR(I51/[1]Допущения!$G$7,0) -> 7.5170903 | L66: Проверка масштабируемости модели
B67: Затраты ИТ как доля GMV за 5 лет | E67: =IFERROR(J51/SUM([1]Допущения!$C$10:$G$10),0) -> 0.054756562 | L67: Здоровый маркетплейс — единицы процентов
B68: Доля облачной инфраструктуры в TCO | E68: =IFERROR(J15/J51,0) -> 0.086279668 | L68: Обычно меньше, чем ожидают студенты
B69: Доля транзакционных расходов в TCO | E69: =IFERROR(J32/J51,0) -> 0.65798584 | L69: Растёт быстрее всего вместе с GMV
B70: Доля команды (ФОТ) в TCO | E70: =IFERROR(J40/J51,0) -> 0.095900228 | L70: Как правило, крупнейшая статья
B72: Вывод для ADR (заполнить текстом): какой вариант дешевле, за счёт чего, и какие допущения сильнее всего влияют на результат?
B73: Например: вариант «модульный монолит» дешевле на 5 лет за счёт меньшего ФОТ и SRE, но при росте выше 3М пользователей разрыв сокращается — точка пересмотра решения (см. ADR №1).

Sheet TCO Oracle
B2: TCO на 5 лет — Africa Delivery
B3: Заполняем колонки «Драйвер роста» и «База, $/год (Год 1)». Годы 1–5 считаются автоматически.
B5: Статья затрат | C5: Драйвер роста | D5: База, $/год (Год 1) | E5: Год 1 | F5: Год 2 | G5: Год 3 | H5: Год 4 | I5: Год 5 | J5: Итого 5 лет | K5: Доля | L5: Комментарий / источник
B6: БЛОК 1. Облачная инфраструктура (OpEx)
B7: Compute: ноды / контейнеры / serverless | C7: пользователи | D7: 30000 | E7: {=IF($D7="","",$D7*INDEX([2]Допущения!$C$25:$G$30,MATCH($C7,[2]Допущения!$B$25:$B$30,0),1))} -> 30000 | F7: {=IF($D7="","",$D7*INDEX([2]Допущения!$C$25:$G$30,MATCH($C7,[2]Допущения!$B$25:$B$30,0),2))} -> 120000 | G7: {=IF($D7="","",$D7*INDEX([2]Допущения!$C$25:$G$30,MATCH($C7,[2]Допущения!$B$25:$B$30,0),3))} -> 300000 | H7: {=IF($D7="","",$D7*INDEX([2]Допущения!$C$25:$G$30,MATCH($C7,[2]Допущения!$B$25:$B$30,0),4))} -> 500000 | I7: {=IF($D7="","",$D7*INDEX([2]Допущения!$C$25:$G$30,MATCH($C7,[2]Допущения!$B$25:$B$30,0),5))} -> 700000 | J7: =SUM(E7:I7) -> 1650000 | L7: AWS af-south-1, оценка по калькулятору
B8: Управляемые БД (PostgreSQL, реплики) | C8: пользователи | D8: 18000 | E8: {=IF($D8="","",$D8*INDEX([2]Допущения!$C$25:$G$30,MATCH($C8,[2]Допущения!$B$25:$B$30,0),1))} -> 18000 | F8: {=IF($D8="","",$D8*INDEX([2]Допущения!$C$25:$G$30,MATCH($C8,[2]Допущения!$B$25:$B$30,0),2))} -> 72000 | G8: {=IF($D8="","",$D8*INDEX([2]Допущения!$C$25:$G$30,MATCH($C8,[2]Допущения!$B$25:$B$30,0),3))} -> 180000 | H8: {=IF($D8="","",$D8*INDEX([2]Допущения!$C$25:$G$30,MATCH($C8,[2]Допущения!$B$25:$B$30,0),4))} -> 300000 | I8: {=IF($D8="","",$D8*INDEX([2]Допущения!$C$25:$G$30,MATCH($C8,[2]Допущения!$B$25:$B$30,0),5))} -> 420000 | J8: =SUM(E8:I8) -> 990000 | L8: Managed RDS + read replica
B9: Хранилище объектов и резервные копии | C9: пользователи | D9: 6000 | E9: {=IF($D9="","",$D9*INDEX([2]Допущения!$C$25:$G$30,MATCH($C9,[2]Допущения!$B$25:$B$30,0),1))} -> 6000 | F9: {=IF($D9="","",$D9*INDEX([2]Допущения!$C$25:$G$30,MATCH($C9,[2]Допущения!$B$25:$B$30,0),2))} -> 24000 | G9: {=IF($D9="","",$D9*INDEX([2]Допущения!$C$25:$G$30,MATCH($C9,[2]Допущения!$B$25:$B$30,0),3))} -> 60000 | H9: {=IF($D9="","",$D9*INDEX([2]Допущения!$C$25:$G$30,MATCH($C9,[2]Допущения!$B$25:$B$30,0),4))} -> 100000 | I9: {=IF($D9="","",$D9*INDEX([2]Допущения!$C$25:$G$30,MATCH($C9,[2]Допущения!$B$25:$B$30,0),5))} -> 140000 | J9: =SUM(E9:I9) -> 330000 | L9: Фото товаров, 5000 SKU на старте
B10: CDN и исходящий трафик | C10: пользователи | D10: 15000 | E10: {=IF($D10="","",$D10*INDEX([2]Допущения!$C$25:$G$30,MATCH($C10,[2]Допущения!$B$25:$B$30,0),1))} -> 15000 | F10: {=IF($D10="","",$D10*INDEX([2]Допущения!$C$25:$G$30,MATCH($C10,[2]Допущения!$B$25:$B$30,0),2))} -> 60000 | G10: {=IF($D10="","",$D10*INDEX([2]Допущения!$C$25:$G$30,MATCH($C10,[2]Допущения!$B$25:$B$30,0),3))} -> 150000 | H10: {=IF($D10="","",$D10*INDEX([2]Допущения!$C$25:$G$30,MATCH($C10,[2]Допущения!$B$25:$B$30,0),4))} -> 250000 | I10: {=IF($D10="","",$D10*INDEX([2]Допущения!$C$25:$G$30,MATCH($C10,[2]Допущения!$B$25:$B$30,0),5))} -> 350000 | J10: =SUM(E10:I10) -> 825000 | L10: 70% трафика — мобильный 3G, картинки WebP
B11: Очереди / стриминг (Kafka, SQS) | C11: пользователи | D11: 12000 | E11: {=IF($D11="","",$D11*INDEX([2]Допущения!$C$25:$G$30,MATCH($C11,[2]Допущения!$B$25:$B$30,0),1))} -> 12000 | F11: {=IF($D11="","",$D11*INDEX([2]Допущения!$C$25:$G$30,MATCH($C11,[2]Допущения!$B$25:$B$30,0),2))} -> 48000 | G11: {=IF($D11="","",$D11*INDEX([2]Допущения!$C$25:$G$30,MATCH($C11,[2]Допущения!$B$25:$B$30,0),3))} -> 120000 | H11: {=IF($D11="","",$D11*INDEX([2]Допущения!$C$25:$G$30,MATCH($C11,[2]Допущения!$B$25:$B$30,0),4))} -> 200000 | I11: {=IF($D11="","",$D11*INDEX([2]Допущения!$C$25:$G$30,MATCH($C11,[2]Допущения!$B$25:$B$30,0),5))} -> 280000 | J11: =SUM(E11:I11) -> 660000 | L11: Асинхронные заказы и уведомления
B12: Резервный регион / DR | C12: пользователи | D12: 24000 | E12: {=IF($D12="","",$D12*INDEX([2]Допущения!$C$25:$G$30,MATCH($C12,[2]Допущения!$B$25:$B$30,0),1))} -> 24000 | F12: {=IF($D12="","",$D12*INDEX([2]Допущения!$C$25:$G$30,MATCH($C12,[2]Допущения!$B$25:$B$30,0),2))} -> 96000 | G12: {=IF($D12="","",$D12*INDEX([2]Допущения!$C$25:$G$30,MATCH($C12,[2]Допущения!$B$25:$B$30,0),3))} -> 240000 | H12: {=IF($D12="","",$D12*INDEX([2]Допущения!$C$25:$G$30,MATCH($C12,[2]Допущения!$B$25:$B$30,0),4))} -> 400000 | I12: {=IF($D12="","",$D12*INDEX([2]Допущения!$C$25:$G$30,MATCH($C12,[2]Допущения!$B$25:$B$30,0),5))} -> 560000 | J12: =SUM(E12:I12) -> 1320000 | L12: Зависит от выбранной стратегии RTO/RPO
B13: Локальное размещение данных (NDPR, Нигерия) | C13: инфляция | D13: 18000 | E13: {=IF($D13="","",$D13*INDEX([2]Допущения!$C$25:$G$30,MATCH($C13,[2]Допущения!$B$25:$B$30,0),1))} -> 18000 | F13: {=IF($D13="","",$D13*INDEX([2]Допущения!$C$25:$G$30,MATCH($C13,[2]Допущения!$B$25:$B$30,0),2))} -> 19440 | G13: {=IF($D13="","",$D13*INDEX([2]Допущения!$C$25:$G$30,MATCH($C13,[2]Допущения!$B$25:$B$30,0),3))} -> 20995.2 | H13: {=IF($D13="","",$D13*INDEX([2]Допущения!$C$25:$G$30,MATCH($C13,[2]Допущения!$B$25:$B$30,0),4))} -> 22674.816 | I13: {=IF($D13="","",$D13*INDEX([2]Допущения!$C$25:$G$30,MATCH($C13,[2]Допущения!$B$25:$B$30,0),5))} -> 24488.801 | J13: =SUM(E13:I13) -> 105598.82 | L13: Локальный провайдер или партнёр — см. ADR №3
C14: фикс | E14: {=IF($D14="","",$D14*INDEX([2]Допущения!$C$25:$G$30,MATCH($C14,[2]Допущения!$B$25:$B$30,0),1))} | F14: {=IF($D14="","",$D14*INDEX([2]Допущения!$C$25:$G$30,MATCH($C14,[2]Допущения!$B$25:$B$30,0),2))} | G14: {=IF($D14="","",$D14*INDEX([2]Допущения!$C$25:$G$30,MATCH($C14,[2]Допущения!$B$25:$B$30,0),3))} | H14: {=IF($D14="","",$D14*INDEX([2]Допущения!$C$25:$G$30,MATCH($C14,[2]Допущения!$B$25:$B$30,0),4))} | I14: {=IF($D14="","",$D14*INDEX([2]Допущения!$C$25:$G$30,MATCH($C14,[2]Допущения!$B$25:$B$30,0),5))} | J14: =SUM(E14:I14) -> 0 | L14: Своя статья
B15: Итого по блоку | E15: =SUM(E7:E14) -> 123000 | F15: =SUM(F7:F14) -> 439440 | G15: =SUM(G7:G14) -> 1070995.2 | H15: =SUM(H7:H14) -> 1772674.8 | I15: =SUM(I7:I14) -> 2474488.8 | J15: =SUM(J7:J14) -> 5880598.8 | K15: =IFERROR(J15/$J$51,0) -> 0.090625253
B17: БЛОК 2. Лицензии, SaaS и инструменты
B18: Observability (метрики, логи, трейсинг) | C18: пользователи | D18: 18000 | E18: {=IF($D18="","",$D18*INDEX([2]Допущения!$C$25:$G$30,MATCH($C18,[2]Допущения!$B$25:$B$30,0),1))} -> 18000 | F18: {=IF($D18="","",$D18*INDEX([2]Допущения!$C$25:$G$30,MATCH($C18,[2]Допущения!$B$25:$B$30,0),2))} -> 72000 | G18: {=IF($D18="","",$D18*INDEX([2]Допущения!$C$25:$G$30,MATCH($C18,[2]Допущения!$B$25:$B$30,0),3))} -> 180000 | H18: {=IF($D18="","",$D18*INDEX([2]Допущения!$C$25:$G$30,MATCH($C18,[2]Допущения!$B$25:$B$30,0),4))} -> 300000 | I18: {=IF($D18="","",$D18*INDEX([2]Допущения!$C$25:$G$30,MATCH($C18,[2]Допущения!$B$25:$B$30,0),5))} -> 420000 | J18: =SUM(E18:I18) -> 990000 | L18: Объём логов растёт с нагрузкой
B19: CI/CD, репозиторий, артефакты | C19: инфляция | D19: 7200 | E19: {=IF($D19="","",$D19*INDEX([2]Допущения!$C$25:$G$30,MATCH($C19,[2]Допущения!$B$25:$B$30,0),1))} -> 7200 | F19: {=IF($D19="","",$D19*INDEX([2]Допущения!$C$25:$G$30,MATCH($C19,[2]Допущения!$B$25:$B$30,0),2))} -> 7776 | G19: {=IF($D19="","",$D19*INDEX([2]Допущения!$C$25:$G$30,MATCH($C19,[2]Допущения!$B$25:$B$30,0),3))} -> 8398.08 | H19: {=IF($D19="","",$D19*INDEX([2]Допущения!$C$25:$G$30,MATCH($C19,[2]Допущения!$B$25:$B$30,0),4))} -> 9069.9264 | I19: {=IF($D19="","",$D19*INDEX([2]Допущения!$C$25:$G$30,MATCH($C19,[2]Допущения!$B$25:$B$30,0),5))} -> 9795.5205 | J19: =SUM(E19:I19) -> 42239.527 | L19: GitHub / GitLab, тарифы на команду
B20: Безопасность: WAF, секреты, антифрод | C20: пользователи | D20: 12000 | E20: {=IF($D20="","",$D20*INDEX([2]Допущения!$C$25:$G$30,MATCH($C20,[2]Допущения!$B$25:$B$30,0),1))} -> 12000 | F20: {=IF($D20="","",$D20*INDEX([2]Допущения!$C$25:$G$30,MATCH($C20,[2]Допущения!$B$25:$B$30,0),2))} -> 48000 | G20: {=IF($D20="","",$D20*INDEX([2]Допущения!$C$25:$G$30,MATCH($C20,[2]Допущения!$B$25:$B$30,0),3))} -> 120000 | H20: {=IF($D20="","",$D20*INDEX([2]Допущения!$C$25:$G$30,MATCH($C20,[2]Допущения!$B$25:$B$30,0),4))} -> 200000 | I20: {=IF($D20="","",$D20*INDEX([2]Допущения!$C$25:$G$30,MATCH($C20,[2]Допущения!$B$25:$B$30,0),5))} -> 280000 | J20: =SUM(E20:I20) -> 660000 | L20: Мошенничество на ПВЗ — риск из кейса
B21: WhatsApp Business API (подписка) | C21: инфляция | D21: 3000 | E21: {=IF($D21="","",$D21*INDEX([2]Допущения!$C$25:$G$30,MATCH($C21,[2]Допущения!$B$25:$B$30,0),1))} -> 3000 | F21: {=IF($D21="","",$D21*INDEX([2]Допущения!$C$25:$G$30,MATCH($C21,[2]Допущения!$B$25:$B$30,0),2))} -> 3240 | G21: {=IF($D21="","",$D21*INDEX([2]Допущения!$C$25:$G$30,MATCH($C21,[2]Допущения!$B$25:$B$30,0),3))} -> 3499.2 | H21: {=IF($D21="","",$D21*INDEX([2]Допущения!$C$25:$G$30,MATCH($C21,[2]Допущения!$B$25:$B$30,0),4))} -> 3779.136 | I21: {=IF($D21="","",$D21*INDEX([2]Допущения!$C$25:$G$30,MATCH($C21,[2]Допущения!$B$25:$B$30,0),5))} -> 4081.4669 | J21: =SUM(E21:I21) -> 17599.803 | L21: Канал для продавцов без личного кабинета
B22: Прочее ПО и подписки | C22: инфляция | D22: 4800 | E22: {=IF($D22="","",$D22*INDEX([2]Допущения!$C$25:$G$30,MATCH($C22,[2]Допущения!$B$25:$B$30,0),1))} -> 4800 | F22: {=IF($D22="","",$D22*INDEX([2]Допущения!$C$25:$G$30,MATCH($C22,[2]Допущения!$B$25:$B$30,0),2))} -> 5184 | G22: {=IF($D22="","",$D22*INDEX([2]Допущения!$C$25:$G$30,MATCH($C22,[2]Допущения!$B$25:$B$30,0),3))} -> 5598.72 | H22: {=IF($D22="","",$D22*INDEX([2]Допущения!$C$25:$G$30,MATCH($C22,[2]Допущения!$B$25:$B$30,0),4))} -> 6046.6176 | I22: {=IF($D22="","",$D22*INDEX([2]Допущения!$C$25:$G$30,MATCH($C22,[2]Допущения!$B$25:$B$30,0),5))} -> 6530.347 | J22: =SUM(E22:I22) -> 28159.685 | L22: Таск-трекер, дизайн, аналитика
B23: Лицензии СУБД Oracle Enterprise | C23: инфляция | D23: 200000 | E23: {=IF($D23="","",$D23*INDEX([2]Допущения!$C$25:$G$30,MATCH($C23,[2]Допущения!$B$25:$B$30,0),1))} -> 200000 | F23: {=IF($D23="","",$D23*INDEX([2]Допущения!$C$25:$G$30,MATCH($C23,[2]Допущения!$B$25:$B$30,0),2))} -> 216000 | G23: {=IF($D23="","",$D23*INDEX([2]Допущения!$C$25:$G$30,MATCH($C23,[2]Допущения!$B$25:$B$30,0),3))} -> 233280 | H23: {=IF($D23="","",$D23*INDEX([2]Допущения!$C$25:$G$30,MATCH($C23,[2]Допущения!$B$25:$B$30,0),4))} -> 251942.4 | I23: {=IF($D23="","",$D23*INDEX([2]Допущения!$C$25:$G$30,MATCH($C23,[2]Допущения!$B$25:$B$30,0),5))} -> 272097.79 | J23: =SUM(E23:I23) -> 1173320.2 | L23: Своя статья
B24: Итого по блоку | E24: =SUM(E18:E23) -> 245000 | F24: =SUM(F18:F23) -> 352200 | G24: =SUM(G18:G23) -> 550776 | H24: =SUM(H18:H23) -> 770838.08 | I24: =SUM(I18:I23) -> 992505.13 | J24: =SUM(J18:J23) -> 2911319.2 | K24: =IFERROR(J24/$J$51,0) -> 0.044866016
B26: БЛОК 3. Транзакционные расходы (Buy / Partner)
B27: Комиссии платёжных провайдеров | C27: GMV | D27: 225000 | E27: {=IF($D27="","",$D27*INDEX([2]Допущения!$C$25:$G$30,MATCH($C27,[2]Допущения!$B$25:$B$30,0),1))} -> 225000 | F27: {=IF($D27="","",$D27*INDEX([2]Допущения!$C$25:$G$30,MATCH($C27,[2]Допущения!$B$25:$B$30,0),2))} -> 1404000 | G27: {=IF($D27="","",$D27*INDEX([2]Допущения!$C$25:$G$30,MATCH($C27,[2]Допущения!$B$25:$B$30,0),3))} -> 4860000 | H27: {=IF($D27="","",$D27*INDEX([2]Допущения!$C$25:$G$30,MATCH($C27,[2]Допущения!$B$25:$B$30,0),4))} -> 10080000 | I27: {=IF($D27="","",$D27*INDEX([2]Допущения!$C$25:$G$30,MATCH($C27,[2]Допущения!$B$25:$B$30,0),5))} -> 15660000 | J27: =SUM(E27:I27) -> 32229000 | L27: ≈3% от GMV: M-Pesa (Кения), Flutterwave / Paystack (Нигерия)
B28: SMS-уведомления | C28: заказы | D28: 12000 | E28: {=IF($D28="","",$D28*INDEX([2]Допущения!$C$25:$G$30,MATCH($C28,[2]Допущения!$B$25:$B$30,0),1))} -> 12000 | F28: {=IF($D28="","",$D28*INDEX([2]Допущения!$C$25:$G$30,MATCH($C28,[2]Допущения!$B$25:$B$30,0),2))} -> 72000 | G28: {=IF($D28="","",$D28*INDEX([2]Допущения!$C$25:$G$30,MATCH($C28,[2]Допущения!$B$25:$B$30,0),3))} -> 240000 | H28: {=IF($D28="","",$D28*INDEX([2]Допущения!$C$25:$G$30,MATCH($C28,[2]Допущения!$B$25:$B$30,0),4))} -> 480000 | I28: {=IF($D28="","",$D28*INDEX([2]Допущения!$C$25:$G$30,MATCH($C28,[2]Допущения!$B$25:$B$30,0),5))} -> 720000 | J28: =SUM(E28:I28) -> 1524000 | L28: ≈$0,04 за SMS × заказы
B29: WhatsApp-сообщения (за диалог) | C29: заказы | D29: 9000 | E29: {=IF($D29="","",$D29*INDEX([2]Допущения!$C$25:$G$30,MATCH($C29,[2]Допущения!$B$25:$B$30,0),1))} -> 9000 | F29: {=IF($D29="","",$D29*INDEX([2]Допущения!$C$25:$G$30,MATCH($C29,[2]Допущения!$B$25:$B$30,0),2))} -> 54000 | G29: {=IF($D29="","",$D29*INDEX([2]Допущения!$C$25:$G$30,MATCH($C29,[2]Допущения!$B$25:$B$30,0),3))} -> 180000 | H29: {=IF($D29="","",$D29*INDEX([2]Допущения!$C$25:$G$30,MATCH($C29,[2]Допущения!$B$25:$B$30,0),4))} -> 360000 | I29: {=IF($D29="","",$D29*INDEX([2]Допущения!$C$25:$G$30,MATCH($C29,[2]Допущения!$B$25:$B$30,0),5))} -> 540000 | J29: =SUM(E29:I29) -> 1143000 | L29: Тариф Meta за conversation
B30: Логистика: интеграции и комиссии партнёров | C30: заказы | D30: 30000 | E30: {=IF($D30="","",$D30*INDEX([2]Допущения!$C$25:$G$30,MATCH($C30,[2]Допущения!$B$25:$B$30,0),1))} -> 30000 | F30: {=IF($D30="","",$D30*INDEX([2]Допущения!$C$25:$G$30,MATCH($C30,[2]Допущения!$B$25:$B$30,0),2))} -> 180000 | G30: {=IF($D30="","",$D30*INDEX([2]Допущения!$C$25:$G$30,MATCH($C30,[2]Допущения!$B$25:$B$30,0),3))} -> 600000 | H30: {=IF($D30="","",$D30*INDEX([2]Допущения!$C$25:$G$30,MATCH($C30,[2]Допущения!$B$25:$B$30,0),4))} -> 1200000 | I30: {=IF($D30="","",$D30*INDEX([2]Допущения!$C$25:$G$30,MATCH($C30,[2]Допущения!$B$25:$B$30,0),5))} -> 1800000 | J30: =SUM(E30:I30) -> 3810000 | L30: Sendbox (Нигерия), Sendy (Кения)
C31: фикс | E31: {=IF($D31="","",$D31*INDEX([2]Допущения!$C$25:$G$30,MATCH($C31,[2]Допущения!$B$25:$B$30,0),1))} | F31: {=IF($D31="","",$D31*INDEX([2]Допущения!$C$25:$G$30,MATCH($C31,[2]Допущения!$B$25:$B$30,0),2))} | G31: {=IF($D31="","",$D31*INDEX([2]Допущения!$C$25:$G$30,MATCH($C31,[2]Допущения!$B$25:$B$30,0),3))} | H31: {=IF($D31="","",$D31*INDEX([2]Допущения!$C$25:$G$30,MATCH($C31,[2]Допущения!$B$25:$B$30,0),4))} | I31: {=IF($D31="","",$D31*INDEX([2]Допущения!$C$25:$G$30,MATCH($C31,[2]Допущения!$B$25:$B$30,0),5))} | J31: =SUM(E31:I31) -> 0 | L31: Своя статья
B32: Итого по блоку | E32: =SUM(E27:E31) -> 276000 | F32: =SUM(F27:F31) -> 1710000 | G32: =SUM(G27:G31) -> 5880000 | H32: =SUM(H27:H31) -> 12120000 | I32: =SUM(I27:I31) -> 18720000 | J32: =SUM(J27:J31) -> 38706000 | K32: =IFERROR(J32/$J$51,0) -> 0.59649386
B34: БЛОК 4. Команда (ФОТ)
B35: Разработка (FTE × годовая ставка) | C35: ФОТ | D35: 960000 | E35: {=IF($D35="","",$D35*INDEX([2]Допущения!$C$25:$G$30,MATCH($C35,[2]Допущения!$B$25:$B$30,0),1))} -> 960000 | F35: {=IF($D35="","",$D35*INDEX([2]Допущения!$C$25:$G$30,MATCH($C35,[2]Допущения!$B$25:$B$30,0),2))} -> 1075200 | G35: {=IF($D35="","",$D35*INDEX([2]Допущения!$C$25:$G$30,MATCH($C35,[2]Допущения!$B$25:$B$30,0),3))} -> 1204224 | H35: {=IF($D35="","",$D35*INDEX([2]Допущения!$C$25:$G$30,MATCH($C35,[2]Допущения!$B$25:$B$30,0),4))} -> 1348730.9 | I35: {=IF($D35="","",$D35*INDEX([2]Допущения!$C$25:$G$30,MATCH($C35,[2]Допущения!$B$25:$B$30,0),5))} -> 1510578.6 | J35: =SUM(E35:I35) -> 6098733.5 | L35: Например 6 FTE × $60k. Зависит от арх. варианта!
B36: DevOps / SRE | C36: ФОТ | D36: 120000 | E36: {=IF($D36="","",$D36*INDEX([2]Допущения!$C$25:$G$30,MATCH($C36,[2]Допущения!$B$25:$B$30,0),1))} -> 120000 | F36: {=IF($D36="","",$D36*INDEX([2]Допущения!$C$25:$G$30,MATCH($C36,[2]Допущения!$B$25:$B$30,0),2))} -> 134400 | G36: {=IF($D36="","",$D36*INDEX([2]Допущения!$C$25:$G$30,MATCH($C36,[2]Допущения!$B$25:$B$30,0),3))} -> 150528 | H36: {=IF($D36="","",$D36*INDEX([2]Допущения!$C$25:$G$30,MATCH($C36,[2]Допущения!$B$25:$B$30,0),4))} -> 168591.36 | I36: {=IF($D36="","",$D36*INDEX([2]Допущения!$C$25:$G$30,MATCH($C36,[2]Допущения!$B$25:$B$30,0),5))} -> 188822.32 | J36: =SUM(E36:I36) -> 762341.68 | L36: Микросервисы требуют больше SRE, чем монолит
B37: Поддержка и дежурства 24/7 | C37: ФОТ | D37: 96000 | E37: {=IF($D37="","",$D37*INDEX([2]Допущения!$C$25:$G$30,MATCH($C37,[2]Допущения!$B$25:$B$30,0),1))} -> 96000 | F37: {=IF($D37="","",$D37*INDEX([2]Допущения!$C$25:$G$30,MATCH($C37,[2]Допущения!$B$25:$B$30,0),2))} -> 107520 | G37: {=IF($D37="","",$D37*INDEX([2]Допущения!$C$25:$G$30,MATCH($C37,[2]Допущения!$B$25:$B$30,0),3))} -> 120422.4 | H37: {=IF($D37="","",$D37*INDEX([2]Допущения!$C$25:$G$30,MATCH($C37,[2]Допущения!$B$25:$B$30,0),4))} -> 134873.09 | I37: {=IF($D37="","",$D37*INDEX([2]Допущения!$C$25:$G$30,MATCH($C37,[2]Допущения!$B$25:$B$30,0),5))} -> 151057.86 | J37: =SUM(E37:I37) -> 609873.35 | L37: Требование mission critical: дежурство ночью
B38: Архитектура и менеджмент | C38: ФОТ | D38: 150000 | E38: {=IF($D38="","",$D38*INDEX([2]Допущения!$C$25:$G$30,MATCH($C38,[2]Допущения!$B$25:$B$30,0),1))} -> 150000 | F38: {=IF($D38="","",$D38*INDEX([2]Допущения!$C$25:$G$30,MATCH($C38,[2]Допущения!$B$25:$B$30,0),2))} -> 168000 | G38: {=IF($D38="","",$D38*INDEX([2]Допущения!$C$25:$G$30,MATCH($C38,[2]Допущения!$B$25:$B$30,0),3))} -> 188160 | H38: {=IF($D38="","",$D38*INDEX([2]Допущения!$C$25:$G$30,MATCH($C38,[2]Допущения!$B$25:$B$30,0),4))} -> 210739.2 | I38: {=IF($D38="","",$D38*INDEX([2]Допущения!$C$25:$G$30,MATCH($C38,[2]Допущения!$B$25:$B$30,0),5))} -> 236027.9 | J38: =SUM(E38:I38) -> 952927.1 | L38: Solution Architect, CTO-функция, PM
C39: фикс | E39: {=IF($D39="","",$D39*INDEX([2]Допущения!$C$25:$G$30,MATCH($C39,[2]Допущения!$B$25:$B$30,0),1))} | F39: {=IF($D39="","",$D39*INDEX([2]Допущения!$C$25:$G$30,MATCH($C39,[2]Допущения!$B$25:$B$30,0),2))} | G39: {=IF($D39="","",$D39*INDEX([2]Допущения!$C$25:$G$30,MATCH($C39,[2]Допущения!$B$25:$B$30,0),3))} | H39: {=IF($D39="","",$D39*INDEX([2]Допущения!$C$25:$G$30,MATCH($C39,[2]Допущения!$B$25:$B$30,0),4))} | I39: {=IF($D39="","",$D39*INDEX([2]Допущения!$C$25:$G$30,MATCH($C39,[2]Допущения!$B$25:$B$30,0),5))} | J39: =SUM(E39:I39) -> 0 | L39: Своя статья
B40: Итого по блоку | E40: =SUM(E35:E39) -> 1326000 | F40: =SUM(F35:F39) -> 1485120 | G40: =SUM(G35:G39) -> 1663334.4 | H40: =SUM(H35:H39) -> 1862934.5 | I40: =SUM(I35:I39) -> 2086486.7 | J40: =SUM(J35:J39) -> 8423875.6 | K40: =IFERROR(J40/$J$51,0) -> 0.12981941
B42: БЛОК 5. Разовые затраты и комплаенс
B43: Юридический и комплаенс-аудит (NDPR, POPIA, KICA) | C43: фикс | D43: 25000 | E43: {=IF($D43="","",$D43*INDEX([2]Допущения!$C$25:$G$30,MATCH($C43,[2]Допущения!$B$25:$B$30,0),1))} -> 25000 | F43: {=IF($D43="","",$D43*INDEX([2]Допущения!$C$25:$G$30,MATCH($C43,[2]Допущения!$B$25:$B$30,0),2))} -> 25000 | G43: {=IF($D43="","",$D43*INDEX([2]Допущения!$C$25:$G$30,MATCH($C43,[2]Допущения!$B$25:$B$30,0),3))} -> 25000 | H43: {=IF($D43="","",$D43*INDEX([2]Допущения!$C$25:$G$30,MATCH($C43,[2]Допущения!$B$25:$B$30,0),4))} -> 25000 | I43: {=IF($D43="","",$D43*INDEX([2]Допущения!$C$25:$G$30,MATCH($C43,[2]Допущения!$B$25:$B$30,0),5))} -> 25000 | J43: =SUM(E43:I43) -> 125000 | L43: Разовая статья — обнули лишние годы вручную
B44: Пентест и аудит безопасности | C44: инфляция | D44: 15000 | E44: {=IF($D44="","",$D44*INDEX([2]Допущения!$C$25:$G$30,MATCH($C44,[2]Допущения!$B$25:$B$30,0),1))} -> 15000 | F44: {=IF($D44="","",$D44*INDEX([2]Допущения!$C$25:$G$30,MATCH($C44,[2]Допущения!$B$25:$B$30,0),2))} -> 16200 | G44: {=IF($D44="","",$D44*INDEX([2]Допущения!$C$25:$G$30,MATCH($C44,[2]Допущения!$B$25:$B$30,0),3))} -> 17496 | H44: {=IF($D44="","",$D44*INDEX([2]Допущения!$C$25:$G$30,MATCH($C44,[2]Допущения!$B$25:$B$30,0),4))} -> 18895.68 | I44: {=IF($D44="","",$D44*INDEX([2]Допущения!$C$25:$G$30,MATCH($C44,[2]Допущения!$B$25:$B$30,0),5))} -> 20407.334 | J44: =SUM(E44:I44) -> 87999.014 | L44: Ежегодно, если mission critical
B45: Миграция данных и интеграции при запуске | C45: фикс | D45: 20000 | E45: {=IF($D45="","",$D45*INDEX([2]Допущения!$C$25:$G$30,MATCH($C45,[2]Допущения!$B$25:$B$30,0),1))} -> 20000 | F45: {=IF($D45="","",$D45*INDEX([2]Допущения!$C$25:$G$30,MATCH($C45,[2]Допущения!$B$25:$B$30,0),2))} -> 20000 | G45: {=IF($D45="","",$D45*INDEX([2]Допущения!$C$25:$G$30,MATCH($C45,[2]Допущения!$B$25:$B$30,0),3))} -> 20000 | H45: {=IF($D45="","",$D45*INDEX([2]Допущения!$C$25:$G$30,MATCH($C45,[2]Допущения!$B$25:$B$30,0),4))} -> 20000 | I45: {=IF($D45="","",$D45*INDEX([2]Допущения!$C$25:$G$30,MATCH($C45,[2]Допущения!$B$25:$B$30,0),5))} -> 20000 | J45: =SUM(E45:I45) -> 100000 | L45: Разовая статья
B46: Обучение команды и найм | C46: ФОТ | D46: 30000 | E46: {=IF($D46="","",$D46*INDEX([2]Допущения!$C$25:$G$30,MATCH($C46,[2]Допущения!$B$25:$B$30,0),1))} -> 30000 | F46: {=IF($D46="","",$D46*INDEX([2]Допущения!$C$25:$G$30,MATCH($C46,[2]Допущения!$B$25:$B$30,0),2))} -> 33600 | G46: {=IF($D46="","",$D46*INDEX([2]Допущения!$C$25:$G$30,MATCH($C46,[2]Допущения!$B$25:$B$30,0),3))} -> 37632 | H46: {=IF($D46="","",$D46*INDEX([2]Допущения!$C$25:$G$30,MATCH($C46,[2]Допущения!$B$25:$B$30,0),4))} -> 42147.84 | I46: {=IF($D46="","",$D46*INDEX([2]Допущения!$C$25:$G$30,MATCH($C46,[2]Допущения!$B$25:$B$30,0),5))} -> 47205.581 | J46: =SUM(E46:I46) -> 190585.42 | L46: Дефицит локальных ИТ-специалистов
C47: фикс | E47: {=IF($D47="","",$D47*INDEX([2]Допущения!$C$25:$G$30,MATCH($C47,[2]Допущения!$B$25:$B$30,0),1))} | F47: {=IF($D47="","",$D47*INDEX([2]Допущения!$C$25:$G$30,MATCH($C47,[2]Допущения!$B$25:$B$30,0),2))} | G47: {=IF($D47="","",$D47*INDEX([2]Допущения!$C$25:$G$30,MATCH($C47,[2]Допущения!$B$25:$B$30,0),3))} | H47: {=IF($D47="","",$D47*INDEX([2]Допущения!$C$25:$G$30,MATCH($C47,[2]Допущения!$B$25:$B$30,0),4))} | I47: {=IF($D47="","",$D47*INDEX([2]Допущения!$C$25:$G$30,MATCH($C47,[2]Допущения!$B$25:$B$30,0),5))} | J47: =SUM(E47:I47) -> 0 | L47: Своя статья
B48: Итого по блоку | E48: =SUM(E43:E47) -> 90000 | F48: =SUM(F43:F47) -> 94800 | G48: =SUM(G43:G47) -> 100128 | H48: =SUM(H43:H47) -> 106043.52 | I48: =SUM(I43:I47) -> 112612.92 | J48: =SUM(J43:J47) -> 503584.44 | K48: =IFERROR(J48/$J$51,0) -> 0.0077606836
B50: Резерв на непредвиденное (contingency) | E50: =(E15+E24+E32+E40+E48)*[2]Допущения!$C$17 -> 309000 | F50: =(F15+F24+F32+F40+F48)*[2]Допущения!$C$17 -> 612234 | G50: =(G15+G24+G32+G40+G48)*[2]Допущения!$C$17 -> 1389785 | H50: =(H15+H24+H32+H40+H48)*[2]Допущения!$C$17 -> 2494873.6 | I50: =(I15+I24+I32+I40+I48)*[2]Допущения!$C$17 -> 3657914 | J50: =SUM(E50:I50) -> 8463806.7 | L50: Расчёт: сумма блоков 1–5 × ставка резерва с листа «Допущения»
B51: ИТОГО прямые затраты (TCO без учёта простоев) | E51: =E15+E24+E32+E40+E48+E50 -> 2369000 | F51: =F15+F24+F32+F40+F48+F50 -> 4693794 | G51: =G15+G24+G32+G40+G48+G50 -> 10655019 | H51: =H15+H24+H32+H40+H48+H50 -> 19127365 | I51: =I15+I24+I32+I40+I48+I50 -> 28044008 | J51: =SUM(E51:I51) -> 64889185
B52: БЛОК 6. Стоимость недоступности (риск)
B53: Ожидаемые потери из-за простоя при целевом SLO | E53: =(1-[2]Допущения!$C$20)*525600*[2]Допущения!$C$19*[2]Допущения!$C$21 -> 630720 | F53: =(1-[2]Допущения!$C$20)*525600*[2]Допущения!$C$19*[2]Допущения!$C$21 -> 630720 | G53: =(1-[2]Допущения!$C$20)*525600*[2]Допущения!$C$19*[2]Допущения!$C$21 -> 630720 | H53: =(1-[2]Допущения!$C$20)*525600*[2]Допущения!$C$19*[2]Допущения!$C$21 -> 630720 | I53: =(1-[2]Допущения!$C$20)*525600*[2]Допущения!$C$19*[2]Допущения!$C$21 -> 630720 | J53: =SUM(E53:I53) -> 3153600 | L53: Расчёт: (1 − SLO) × 525 600 мин/год × стоимость минуты × переключатель. 525 600 — число минут в году
B54: ИТОГО TCO с учётом стоимости простоя | E54: =E51+E53 -> 2999720 | F54: =F51+F53 -> 5324514 | G54: =G51+G53 -> 11285739 | H54: =H51+H53 -> 19758085 | I54: =I51+I53 -> 28674728 | J54: =SUM(E54:I54) -> 68042785
B55: Коэффициент дисконтирования | E55: =1/(1+[2]Допущения!$C$16)^0 -> 1 | F55: =1/(1+[2]Допущения!$C$16)^1 -> 0.83333333 | G55: =1/(1+[2]Допущения!$C$16)^2 -> 0.69444444 | H55: =1/(1+[2]Допущения!$C$16)^3 -> 0.5787037 | I55: =1/(1+[2]Допущения!$C$16)^4 -> 0.48225309
B56: Дисконтированный TCO (NPV затрат) | E56: =E54*E55 -> 2999720 | F56: =F54*F55 -> 4437095 | G56: =G54*G55 -> 7837318.5 | H56: =H54*H55 -> 11434077 | I56: =I54*I55 -> 13828476 | J56: =SUM(E56:I56) -> 40536686
B58: Ключевые метрики
B59: TCO за 5 лет, прямые затраты | E59: =J51 -> 64889185 | L59: Основная цифра для сравнения вариантов в ADR
B60: TCO за 5 лет с учётом простоя | E60: =J54 -> 68042785 | L60: Показывает цену недоступности для mission critical
B61: NPV затрат за 5 лет | E61: =J56 -> 40536686 | L61: Затраты, приведённые к сегодняшнему дню
B62: Средние затраты в год | E62: =J51/5 -> 12977837 | L62: Ориентир для планирования бюджета
B63: Облако, $/мес в Год 1 | E63: =E15/12 -> 10250 | L63: Сравнивается с лимитом CFO
B64: Проверка бюджета CFO на Год 1 | E64: =IF(E15/12<=[2]Допущения!$C$18,"В бюджете CFO","ПРЕВЫШЕНИЕ бюджета") -> ПРЕВЫШЕНИЕ бюджета | L64: Если превышение — объясни в ADR, чем жертвуешь
B65: TCO на 1 заказ за 5 лет | E65: =IFERROR(J51/SUM([2]Допущения!$C$8:$G$8),0) -> 1.7031282 | L65: Юнит-экономика: сколько ИТ стоит в одном заказе
B66: TCO на 1 активного пользователя (Год 5) | E66: =IFERROR(I51/[2]Допущения!$G$7,0) -> 8.0125736 | L66: Проверка масштабируемости модели
B67: Затраты ИТ как доля GMV за 5 лет | E67: =IFERROR(J51/SUM([2]Допущения!$C$10:$G$10),0) -> 0.060401363 | L67: Здоровый маркетплейс — единицы процентов
B68: Доля облачной инфраструктуры в TCO | E68: =IFERROR(J15/J51,0) -> 0.090625253 | L68: Обычно меньше, чем ожидают студенты
B69: Доля транзакционных расходов в TCO | E69: =IFERROR(J32/J51,0) -> 0.59649386 | L69: Растёт быстрее всего вместе с GMV
B70: Доля команды (ФОТ) в TCO | E70: =IFERROR(J40/J51,0) -> 0.12981941 | L70: Как правило, крупнейшая статья
B72: Вывод для ADR (заполнить текстом): какой вариант дешевле, за счёт чего, и какие допущения сильнее всего влияют на результат?
B73: Например: вариант «модульный монолит» дешевле на 5 лет за счёт меньшего ФОТ и SRE, но при росте выше 3М пользователей разрыв сокращается — точка пересмотра решения (см. ADR №1).
